数字系统/VS_verilog_源代码文件/FSMD_summation/summation.v
module summation (
   input clk,reset,
   output reg [7:0] out
);
parameter s0=0,s1=1,s2=2,s3=3,s4=4;
reg [2:0] state;
reg [7:0] sum;
reg [7:0] i;
always @(posedge clk or negedge reset) begin
   if (reset==0) begin
     out<=0;
     state<=s0;
   end
   else begin
     case (state)
      s0:begin
        sum<=0;
        i<=1;
        out<=0;
        state<=s1;
      end
      s1:begin
        sum<=sum+i;
        out<=0;
        state<=s2;
      end
      s2:begin
        out<=0;
        i<=i+1;
        state<=s3;
      end
      s3:begin
        out<=0;
        if(i!=11) 
          state<=s1;
        else 
        state<=s4;
      end
      s4:begin
        out<=sum;
        state<=s4;
      end
      default:begin
        out<=0;
        state<=s0;
      end
     endcase
   end
end
endmodule

数字系统/VS_verilog_源代码文件/FSMD_summation/tb.v
//~ `New testbench
`include "summation.v"
`timescale  1ns / 1ps

module tb_summation;

// summation Parameters
parameter PERIOD = 10;
parameter s0  = 0;

// summation Inputs
reg   clk                                  = 0 ;
reg   reset                                = 0 ;

// summation Outputs
wire  [7:0]  out                           ;


initial
begin
    forever #(PERIOD/2)  clk=~clk;
end



summation #(
    .s0 ( s0 ))
 u_summation (
    .clk                     ( clk          ),
    .reset                   ( reset        ),

    .out                     ( out    [7:0] )
);

initial
begin
    $dumpfile("tb_summation.vcd");
    $dumpvars(0, tb_summation);
    reset=0;
    #10
    reset=1;
    #1000
    $finish;
end

endmodule

数字系统/VS_verilog_源代码文件/FSMD_summation/tb_summation.vcd
$date
	Sat May 13 17:47:59 2023
$end
$version
	Icarus Verilog
$end
$timescale
	1ps
$end
$scope module tb_summation $end
$var wire 8 ! out [7:0] $end
$var reg 1 " clk $end
$var reg 1 # reset $end
$scope module u_summation $end
$var wire 1 " clk $end
$var wire 1 # reset $end
$var reg 8 $ i [7:0] $end
$var reg 8 % out [7:0] $end
$var reg 3 & state [2:0] $end
$var reg 8 ' sum [7:0] $end
$upscope $end
$upscope $end
$enddefinitions $end
#0
$dumpvars
bx '
b0 &
b0 %
bx $
0#
0"
b0 !
$end
#5000
1"
#10000
0"
1#
#15000
b1 &
b1 $
b0 '
1"
#20000
0"
#25000
b10 &
b1 '
1"
#30000
0"
#35000
b11 &
b10 $
1"
#40000
0"
#45000
b1 &
1"
#50000
0"
#55000
b10 &
b11 '
1"
#60000
0"
#65000
b11 &
b11 $
1"
#70000
0"
#75000
b1 &
1"
#80000
0"
#85000
b10 &
b110 '
1"
#90000
0"
#95000
b11 &
b100 $
1"
#100000
0"
#105000
b1 &
1"
#110000
0"
#115000
b10 &
b1010 '
1"
#120000
0"
#125000
b11 &
b101 $
1"
#130000
0"
#135000
b1 &
1"
#140000
0"
#145000
b10 &
b1111 '
1"
#150000
0"
#155000
b11 &
b110 $
1"
#160000
0"
#165000
b1 &
1"
#170000
0"
#175000
b10 &
b10101 '
1"
#180000
0"
#185000
b11 &
b111 $
1"
#190000
0"
#195000
b1 &
1"
#200000
0"
#205000
b10 &
b11100 '
1"
#210000
0"
#215000
b11 &
b1000 $
1"
#220000
0"
#225000
b1 &
1"
#230000
0"
#235000
b10 &
b100100 '
1"
#240000
0"
#245000
b11 &
b1001 $
1"
#250000
0"
#255000
b1 &
1"
#260000
0"
#265000
b10 &
b101101 '
1"
#270000
0"
#275000
b11 &
b1010 $
1"
#280000
0"
#285000
b1 &
1"
#290000
0"
#295000
b10 &
b110111 '
1"
#300000
0"
#305000
b11 &
b1011 $
1"
#310000
0"
#315000
b100 &
1"
#320000
0"
#325000
b110111 !
b110111 %
1"
