数字系统/VS_verilog_源代码文件/verilog/DFF_eable/DFF_eable.v
module DFF_eable #(
    parameter n=4
) (
    input clk,
    input reset,
    input eable,
    input [n-1:0] D,
    output reg [n-1:0] Q=0
); 
    always @(posedge clk or posedge reset) begin
        if (reset==1) begin
            Q<=0;
        end
        else if (eable==1) begin
            Q<=D;
        end
    end
endmodule

数字系统/VS_verilog_源代码文件/verilog/DFF_eable/tb.v
//~ `New testbench
`include "DFF_eable.v"
`timescale  1ns / 1ps

module tb_DFF_eable;

// DFF_eable Parameters
parameter PERIOD = 10;
parameter n  = 4;

// DFF_eable Inputs
reg   clk                                  = 0 ;
reg   reset                                = 0 ;
reg   eable                                = 0 ;
reg   [n-1:0]  D                           = 0 ;

// DFF_eable Outputs
wire  [n-1:0]  Q                           ;


initial
begin
    forever #(PERIOD/2)  clk=~clk;
end


DFF_eable #(
    .n ( n ))
 u_DFF_eable (
    .clk                     ( clk            ),
    .reset                   ( reset          ),
    .eable                   ( eable          ),
    .D                       ( D      [n-1:0] ),

    .Q                       ( Q      [n-1:0] )
);

initial
begin
    $dumpfile("tb_DFF_eable.vcd");
    $dumpvars(0, tb_DFF_eable);
    reset = 1;
    #10
    reset=0;
    eable=1;
    D=0;
    #6
    D=12;
    #6
    D=8;
    #6
    D=4;
    #6
    D=2;
    #6
    eable=0;
    #6
    D=1;
    #6
    D=9;
    #6
    eable=1;
    #6
    D=5;
    #6
    D=13;
    #6
    $finish;
end

endmodule

数字系统/VS_verilog_源代码文件/verilog/DFF_eable/tb_DFF_eable.vcd
$date
	Tue May 02 15:46:28 2023
$end
$version
	Icarus Verilog
$end
$timescale
	1ps
$end
$scope module tb_DFF_eable $end
$var wire 4 ! Q [3:0] $end
$var reg 4 " D [3:0] $end
$var reg 1 # clk $end
$var reg 1 $ eable $end
$var reg 1 % reset $end
$scope module u_DFF_eable $end
$var wire 4 & D [3:0] $end
$var wire 1 # clk $end
$var wire 1 $ eable $end
$var wire 1 % reset $end
$var reg 4 ' Q [3:0] $end
$upscope $end
$upscope $end
$enddefinitions $end
#0
$dumpvars
b0 '
b0 &
1%
0$
0#
b0 "
b0 !
$end
#5000
1#
#10000
0#
1$
0%
#15000
1#
#16000
b1100 "
b1100 &
#20000
0#
#22000
b1000 "
b1000 &
#25000
b1000 !
b1000 '
1#
#28000
b100 "
b100 &
#30000
0#
#34000
b10 "
b10 &
#35000
b10 !
b10 '
1#
#40000
0#
0$
#45000
1#
#46000
b1 "
b1 &
#50000
0#
#52000
b1001 "
b1001 &
#55000
1#
#58000
1$
#60000
0#
#64000
b101 "
b101 &
#65000
b101 !
b101 '
1#
#70000
0#
b1101 "
b1101 &
#75000
b1101 !
b1101 '
1#
