数字系统/VS_verilog_源代码文件/verilog/regfile/regfile.v
module regfile 
 (
    input [7:0]  D,
    input [1:0] WA,
    input WE,
    input clk,
    input [1:0] RAA,RBA,
    input RAE, RBE,
    output reg [7:0]  portA,
    output reg [7:0]  portB
);
    reg [7:0]  reg1 , reg2, reg3, reg4;
    always @(posedge clk) begin
      if (WE) 
       case (WA)
       0: reg1 <= D;
         1: reg2 <= D;
            2: reg3 <= D;
                3: reg4 <= D;
         endcase
    end

    always @(RAA,RAE) begin
      if (RAE) begin
         case (RAA)
         0: portA <= reg1;
            1: portA <= reg2;
                2: portA <= reg3;
                 3: portA <= reg4;
                 default : portA <= 8'h00;
            endcase
        end
        else begin
          portA <= 8'h00;
        end
    end


    always @(RBA,RBE) begin
      if (RBE) begin
            case (RBA)
            0: portB <= reg1;
                1: portB <= reg2;
                    2: portB <= reg3;
                    3: portB <= reg4;
                    default : portB <= 8'h00;
                endcase
            end
            else begin
            portB <= 8'h00;
            end
    end
    endmodule

数字系统/VS_verilog_源代码文件/verilog/regfile/tb.v
//~ `New testbench
`include "regfile.v"
`timescale  1ns / 1ps

module tb_regfile;

// regfile Parameters
parameter PERIOD  = 10;


// regfile Inputs
reg   [7:0]  D                             = 0 ;
reg   [1:0]  WA                            = 0 ;
reg   WE                                   = 0 ;
reg   clk                                  = 0 ;
reg   [1:0]  RAA                           = 0 ;
reg   [1:0]  RBA                           = 0 ;
reg   RAE                                  = 0 ;
reg   RBE                                  = 0 ;

// regfile Outputs
wire  [7:0]  portA                         ;
wire  [7:0]  portB                         ;


initial
begin
    forever #(PERIOD/2)  clk=~clk;
end



regfile  u_regfile (
    .D                       ( D      [7:0] ),
    .WA                      ( WA     [1:0] ),
    .WE                      ( WE           ),
    .clk                     ( clk          ),
    .RAA                     ( RAA    [1:0] ),
    .RBA                     ( RBA    [1:0] ),
    .RAE                     ( RAE          ),
    .RBE                     ( RBE          ),

    .portA                   ( portA  [7:0] ),
    .portB                   ( portB  [7:0] )
);

initial
begin
    $dumpfile("tb_regfile.vcd");
    $dumpvars(0, tb_regfile);
    D = 23 ;
    RAE=1;
    RBE=1;
    RAA=0;
    RBA=0;
    WE=1;
    WA=3;
    #10
    D = 45 ;
    WA=1;
    RAA=3;
    RBA=1;
    #10
    D = 67 ;
    WA=2;
    #10
    D = 89 ;
    WA=0;
    #10


    $finish;
end

endmodule

数字系统/VS_verilog_源代码文件/verilog/regfile/tb_regfile.vcd
$date
	Wed May 03 01:34:07 2023
$end
$version
	Icarus Verilog
$end
$timescale
	1ps
$end
$scope module tb_regfile $end
$var wire 8 ! portB [7:0] $end
$var wire 8 " portA [7:0] $end
$var reg 8 # D [7:0] $end
$var reg 2 $ RAA [1:0] $end
$var reg 1 % RAE $end
$var reg 2 & RBA [1:0] $end
$var reg 1 ' RBE $end
$var reg 2 ( WA [1:0] $end
$var reg 1 ) WE $end
$var reg 1 * clk $end
$scope module u_regfile $end
$var wire 8 + D [7:0] $end
$var wire 2 , RAA [1:0] $end
$var wire 1 % RAE $end
$var wire 2 - RBA [1:0] $end
$var wire 1 ' RBE $end
$var wire 2 . WA [1:0] $end
$var wire 1 ) WE $end
$var wire 1 * clk $end
$var reg 8 / portA [7:0] $end
$var reg 8 0 portB [7:0] $end
$var reg 8 1 reg1 [7:0] $end
$var reg 8 2 reg2 [7:0] $end
$var reg 8 3 reg3 [7:0] $end
$var reg 8 4 reg4 [7:0] $end
$upscope $end
$upscope $end
$enddefinitions $end
#0
$dumpvars
bx 4
bx 3
bx 2
bx 1
bx 0
bx /
b11 .
b0 -
b0 ,
b10111 +
0*
1)
b11 (
1'
b0 &
1%
b0 $
b10111 #
bx "
bx !
$end
#5000
b10111 4
1*
#10000
b10111 "
b10111 /
0*
b1 &
b1 -
b11 $
b11 ,
b1 (
b1 .
b101101 #
b101101 +
#15000
b101101 2
1*
#20000
0*
b10 (
b10 .
b1000011 #
b1000011 +
#25000
b1000011 3
1*
#30000
0*
b0 (
b0 .
b1011001 #
b1011001 +
#35000
b1011001 1
1*
