数字系统/VS_verilog_源代码文件/verilog/lab4/FSM.v
module FSM (
    input clk,
    input rst,
    input b0,b1,
    output  reg  unlock,
    output  [2:0] debugstate
    );
    parameter s_reset = 0;
    parameter s_1 = 1;
    parameter s_10 = 2;
    parameter s_100 = 3;
    parameter s_1001 = 4;
    parameter s_10010 = 5;
    reg[2:0] state,next_state;
    
    assign debugstate=state;
    always@(posedge clk or negedge rst) begin
        if(!rst) begin
            state <= s_reset;
        end
        else begin
            state <= next_state;
        end
    end

    always @(posedge clk or negedge rst) begin
        if (!rst) unlock=0;
        else begin case (next_state)
            s_reset: unlock<=0;
            s_1: unlock<=0;
            s_10: unlock<=0;
            s_100: unlock<=0;
            s_1001: unlock<=0;
            s_10010: unlock<=1;
            default: unlock<=0;
        endcase
        end
    end

    always @(state or b0 or b1)
    begin
        case (state)
        s_reset: begin
            if ({b0,b1}==2'b01) next_state=s_1;
            else next_state=s_reset;
        end
        s_1: begin
            if ({b0,b1}==2'b10) next_state=s_10;
            else next_state=s_1;
        end
        s_10: begin
            if ({b0,b1}==2'b10) next_state=s_100;
            else if ({b0,b1}==2'b01) next_state=s_1;
            else next_state=s_10;
        end
        s_100: begin
            if ({b0,b1}==2'b01) next_state=s_1001;
            else if ({b0,b1}==2'b10) next_state=s_reset;
            else next_state=s_100;
        end
        s_1001: begin
            if ({b0,b1}==2'b10) next_state=s_10010;
            else if ({b0,b1}==2'b01) next_state=s_1;
            else next_state=s_1001;
        end
        s_10010: begin
            if ({b0,b1}==2'b10) next_state=s_reset;
            else if ({b0,b1}==2'b01) next_state=s_100;
            else next_state=s_10010;
        end
        endcase
    end
endmodule

数字系统/VS_verilog_源代码文件/verilog/FSM_lab4/tb.v
//~ `New testbench
`include "FSM.v"
`timescale  1ns / 1ps

module tb_FSM;

// FSM Parameters
parameter PERIOD   = 10;
parameter s_reset  = 0;
parameter s_1      = 1;
parameter s_10     = 2;
parameter s_100    = 3;
parameter s_1001   = 4;
parameter s_10010  = 5;

// FSM Inputs
reg   clk                                  = 0 ;
reg   rst                                  = 0 ;
reg   b0                                   = 0 ;
reg   b1                                   = 0 ;

// FSM Outputs
wire  unlock                               ;
wire  [2:0]  debugstate                    ;


initial
begin
    forever #(PERIOD/2)  clk=~clk;
end



FSM #(
    .s_reset ( s_reset ),
    .s_1     ( s_1     ),
    .s_10    ( s_10    ),
    .s_100   ( s_100   ),
    .s_1001  ( s_1001  ),
    .s_10010 ( s_10010 ))
 u_FSM (
    .clk                     ( clk               ),
    .rst                     ( rst               ),
    .b0                      ( b0                ),
    .b1                      ( b1                ),

    .unlock                  ( unlock            ),
    .debugstate              ( debugstate  [2:0] )
);

initial
begin
    $dumpfile("tb_FSM.vcd");
    $dumpvars(0,tb_FSM);
    b0 = 0;
    b1 = 0;
    rst = 0;
    #5
    rst = 1;
    #10
    b1=1;
    #10
    b1=0;
    b0=1;
    #10
    b0=1;
    b1=0;
    #10
    b0=0;
    b1=0;
    #30
    b0=0;
    b1=1;
    #10
    b0=1;
    b1=0;
    #10
    b0=0;
    b1=1;
    #10


    $finish;
end

endmodule

数字系统/VS_verilog_源代码文件/verilog/FSM_lab4/tb_FSM.vcd
$date
	Thu May 11 00:33:42 2023
$end
$version
	Icarus Verilog
$end
$timescale
	1ps
$end
$scope module tb_FSM $end
$var wire 1 ! unlock $end
$var wire 3 " debugstate [2:0] $end
$var reg 1 # b0 $end
$var reg 1 $ b1 $end
$var reg 1 % clk $end
$var reg 1 & rst $end
$scope module u_FSM $end
$var wire 1 # b0 $end
$var wire 1 $ b1 $end
$var wire 1 % clk $end
$var wire 3 ' debugstate [2:0] $end
$var wire 1 & rst $end
$var reg 3 ( next_state [2:0] $end
$var reg 3 ) state [2:0] $end
$var reg 1 ! unlock $end
$upscope $end
$upscope $end
$enddefinitions $end
#0
$dumpvars
b0 )
b0 (
b0 '
0&
0%
0$
0#
b0 "
0!
$end
#5000
1&
1%
#10000
0%
#15000
b1 "
b1 '
b1 )
b1 (
1%
1$
#20000
0%
#25000
b10 "
b10 '
b10 )
b11 (
1%
1#
0$
#30000
0%
#35000
b0 (
b11 "
b11 '
b11 )
1%
#40000
0%
#45000
b11 (
1%
0#
#50000
0%
#55000
1%
#60000
0%
#65000
1%
#70000
0%
#75000
b100 "
b100 '
b100 )
b1 (
1%
1$
#80000
0%
#85000
1!
b101 "
b101 '
b101 )
b0 (
1%
0$
1#
#90000
0%
#95000
b11 "
b11 '
b11 )
0!
b100 (
1%
1$
0#
#100000
0%
#105000
b1 (
b100 "
b100 '
b100 )
1%
