数字系统/VS_verilog_源代码文件/verilog/lab4/Segment.v
`timescale 1ns/1ns
module Segment(
    Clk,
    Reset_N,
    Disp_Data,
    state,
    Sel,
    DisPlay,
    DisPlay1
    );
    input Clk;
    input Reset_N;
    input [31:0]Disp_Data;
    input [2:0]state; 
    output reg [7:0]Sel;
    output reg [7:0]DisPlay;
    output reg [7:0]DisPlay1;
    
    reg clk_1k;
    reg [15:0]div_cnt;


    always@(posedge Clk or negedge Reset_N)
    if(!Reset_N)
        div_cnt <= 0;
    else if(div_cnt >= 499)
        div_cnt <= 0;
    else
        div_cnt <= div_cnt + 1'd1;
    
    // clk_1k采用使能时钟，避免使用门控时钟
    always@(posedge Clk or negedge Reset_N)
    if(!Reset_N)
        clk_1k <= 0;
    else if(div_cnt == 499)
        clk_1k <= 1'b1;
    else
        clk_1k <= 0;
    
    
    reg [2:0]Num;
    always@(posedge Clk or negedge Reset_N)
    if(!Reset_N)
        Num <= 0;
    else if(clk_1k) begin
        if (state!=0) Num <= (Num==state-1)?  0 :Num + 1'd1;
        else Num <= 0;
    end
    
       
    
    // 3_8译码器
    always@(posedge Clk)
    case (state)
    3'b000:begin
            Sel = 8'b0000_0000;
    end
    3'b001:begin
              case(Num)
            3'b000: Sel = 8'b0000_0001;
        endcase
    end
    3'b010:begin
              case(Num)
            3'b000: Sel = 8'b0000_0001;
            3'b001: Sel = 8'b0000_0010;
        endcase
    end
    3'b011:begin
              case(Num)
            3'b000: Sel = 8'b0000_0001;
            3'b001: Sel = 8'b0000_0010;
            3'b010: Sel = 8'b0000_0100;
        endcase
    end
    3'b100:begin
              case(Num)
            3'b000: Sel = 8'b0000_0001;
            3'b001: Sel = 8'b0000_0010;
            3'b010: Sel = 8'b0000_0100;
            3'b011: Sel = 8'b0000_1000;
        endcase
    end
    3'b101:begin
              case(Num)
            3'b000: Sel = 8'b0000_0001;
            3'b001: Sel = 8'b0000_0010;
            3'b010: Sel = 8'b0000_0100;
            3'b011: Sel = 8'b0000_1000;
            3'b100: Sel = 8'b0001_0000;
    endcase
    end
    endcase

    


            //       case(Num)
            // 3'b000: Sel = 8'b0000_0001;
            // 3'b001: Sel = 8'b0000_0010;
            // 3'b010: Sel = 8'b0000_0100;
            // 3'b011: Sel = 8'b0000_1000;
            // 3'b100: Sel = 8'b0001_0000;
            // 3'b101: Sel = 8'b0010_0000;
            // 3'b110: Sel = 8'b0100_0000;
            // 3'b111: Sel = 8'b1000_0000;



    // 8选1多路器
    reg [3:0]Disp_tmp;
    reg [3:0]Disp_tmp1;
    always@(posedge Clk)
        case(Num)
            3'b000: Disp_tmp = Disp_Data[3:0];
            3'b001: Disp_tmp = Disp_Data[7:4];
            3'b010: Disp_tmp = Disp_Data[11:8];
            3'b011: Disp_tmp = Disp_Data[15:12];
            3'b100: Disp_tmp1 = Disp_Data[19:16];
            3'b101: Disp_tmp1 = Disp_Data[23:20];
            3'b110: Disp_tmp1 = Disp_Data[27:24];
            3'b111: Disp_tmp1 = Disp_Data[31:28];
        endcase
    always@(posedge Clk)
        case(Disp_tmp)
            0:  DisPlay = ~8'hc0;
            1:  DisPlay = ~8'hf9;
            2:  DisPlay = ~8'ha4;
            3:  DisPlay = ~8'hb0;
            4:  DisPlay = ~8'h99;
            5:  DisPlay = ~8'h92;
            6:  DisPlay = ~8'h82;
            7:  DisPlay = ~8'hf8;
            8:  DisPlay = ~8'h80;
            9:  DisPlay = ~8'h90;
            10: DisPlay = ~8'h88;
            11: DisPlay = ~8'h83;
            12: DisPlay = ~8'hc6;
            13: DisPlay = ~8'ha1;
            14: DisPlay = ~8'h86;
            15: DisPlay = ~8'h8e;
        endcase  
    always@(posedge Clk)
        case(Disp_tmp1)
            0:  DisPlay1 = ~8'hc0;
            1:  DisPlay1 = ~8'hf9;
            2:  DisPlay1 = ~8'ha4;
            3:  DisPlay1 = ~8'hb0;
            4:  DisPlay1 = ~8'h99;
            5:  DisPlay1 = ~8'h92;
            6:  DisPlay1 = ~8'h82;
            7:  DisPlay1 = ~8'hf8;
            8:  DisPlay1 = ~8'h80;
            9:  DisPlay1 = ~8'h90;
            10: DisPlay1 = ~8'h88;
            11: DisPlay1 = ~8'h83;
            12: DisPlay1 = ~8'hc6;
            13: DisPlay1 = ~8'ha1;
            14: DisPlay1 = ~8'h86;
            15: DisPlay1 = ~8'h8e;
        endcase  

endmodule

数字系统/VS_verilog_源代码文件/verilog/lab4/FSM.v
module FSM (
    input clk,
    input rst,
    input b0,b1,
    output  reg  unlock,
    output  [2:0] debugstate
    );
    parameter s_reset = 0;
    parameter s_1 = 1;
    parameter s_10 = 2;
    parameter s_100 = 3;
    parameter s_1001 = 4;
    parameter s_10010 = 5;
    reg[2:0] state,next_state;
    
    assign debugstate=state;
    always@(posedge clk or negedge rst) begin
        if(!rst) begin
            state <= s_reset;
        end
        else begin
            state <= next_state;
        end
    end

    always @(posedge clk or negedge rst) begin
        if (!rst) unlock=0;
        else begin case (next_state)
            s_reset: unlock<=0;
            s_1: unlock<=0;
            s_10: unlock<=0;
            s_100: unlock<=0;
            s_1001: unlock<=0;
            s_10010: unlock<=1;
            default: unlock<=0;
        endcase
        end
    end

    always @(state or b0 or b1)
    begin
        case (state)
        s_reset: begin
            if ({b0,b1}==2'b01) next_state=s_1;
            else next_state=s_reset;
        end
        s_1: begin
            if ({b0,b1}==2'b10) next_state=s_10;
            else next_state=s_1;
        end
        s_10: begin
            if ({b0,b1}==2'b10) next_state=s_100;
            else if ({b0,b1}==2'b01) next_state=s_1;
            else next_state=s_10;
        end
        s_100: begin
            if ({b0,b1}==2'b01) next_state=s_1001;
            else if ({b0,b1}==2'b10) next_state=s_reset;
            else next_state=s_100;
        end
        s_1001: begin
            if ({b0,b1}==2'b10) next_state=s_10010;
            else if ({b0,b1}==2'b01) next_state=s_1;
            else next_state=s_1001;
        end
        s_10010: begin
            if ({b0,b1}==2'b10) next_state=s_reset;
            else if ({b0,b1}==2'b01) next_state=s_100;
            else next_state=s_10010;
        end
        endcase
    end
endmodule

数字系统/VS_verilog_源代码文件/verilog/lab4/botton.v
module botton(
		input 	wire		clk		,		//50MHz时钟频率
		input 	wire		rst_n	,		//复位按键
		input 	wire		key		,		//按键输入口
		output 	reg 		press			//按键按下标志输出
	);
	
	//全局参数定义
	parameter	DELAY_TIME = 50;	//延时20ms也就是1000_000个时钟周期
	
	//信号定义
	reg				key_r0		;		//同步 当前时钟周期输入状态
	reg				key_r1		;		//打拍 前一个时钟周期输入的状态
	wire			key_nedge	;		//下降沿
	
	reg		[19:0]	delay_cnt	;		//计数20ms，需要20ms/20ns = 1000_000个时钟周期
	reg				delay_flag	;		//按下的下降沿标志
	initial begin
		delay_cnt=0;
	end
	//同步计数实现
	always @(posedge clk or negedge rst_n) begin
		if(rst_n == 1'b0) begin
			key_r0 <= 1'b1;
			key_r1 <= 1'b1;
		end
		else begin
			key_r0 <= key;
			key_r1 <= key_r0;
		end
	end
	
	assign key_nedge = key_r0 & ~key_r1;	//检测下降沿
	//assign key_pedge = key_r0 & ~key_r1;	//检测上升沿
	
	//delay_cnt 计数器计满1000_000个时钟周期
	always @(posedge clk or negedge rst_n) begin
		if(!rst_n) begin
			delay_cnt <= 0;
		end
		else if(delay_flag) begin
			//按下的下降沿标志出现，则执行
			if(delay_cnt == DELAY_TIME - 1) begin
				//如果计满1000_000个时钟周期，则归零处理
				delay_cnt <= 0;
			end
			else begin
				//没有计满，则不断累加
				delay_cnt <= delay_cnt + 1;
			end
		end
	end
	
	//delay_flag
	always @(posedge clk or negedge rst_n) begin
		if(!rst_n) begin
			delay_flag <= 1'b0;
		end
		else if(key_nedge) begin
			//下降沿出现后，设置按下标志位为 1
			delay_flag <= 1'b1;
		end
		else if(delay_cnt == DELAY_TIME - 1) begin
			/*
			计数器计满1000_000个时钟周期后，
			设置按下标志位为 0
			表示按键按下结束，以备下次按键
			*/
			delay_flag <= 1'b0;
		end
	end
	
	//press
	always @(posedge clk or negedge rst_n) begin
		if(!rst_n) begin
			press <= 1'b0;
		end
		else if(delay_cnt == DELAY_TIME - 1) begin
			/*
			计满1000_000个时钟周期后
			获取当前的按压标志
			此时 press = 1
			*/
			press <= key_r0;
			// 上升沿时press<=key_r0;
		end
		else begin
			/*
			没有计满1000_000个时钟周期
			则 press = 0
			*/
			press <= 1'b0;
		end
	end

endmodule

数字系统/VS_verilog_源代码文件/verilog/lab4/top.v
`include "botton.v"
`include "FSM.v"
`include "Segment.v"

module top (
    input clk,
    input rst,
    input key0,key1,
    output  [0:0]unlock,
    output  [7:0]Sel,
    output  [7:0]DisPlay,
    output  [7:0]DisPlay1
);
   wire b0,b1;
   wire [2:0] current_state;
   reg  [31:0] data;
   botton u_botton(
       .clk(clk),
       .rst_n(rst),
       .key(key0),
       .press(b0)
   );
    botton u_botton1(
         .clk(clk),
         .rst_n(rst),
         .key(key1),
         .press(b1)
    );
   FSM u_FSM(
       .clk(clk),
       .rst(rst),
       .b0(b0),
       .b1(b1),
       .unlock(unlock),
       .debugstate(current_state)
   );
    always @(posedge clk ) begin
        case (current_state)
   3'b000: data<=32'h00000000;
   3'b001: data<=32'h00000001;
   3'b010: data<=32'h00000010;
   3'b011: data<=32'h00000100;
   3'b100: data<=32'h00001001;
   3'b101: data<=32'h00010010;
        endcase
    end
    
    Segment u_Segment(
         .Clk(clk),
         .Reset_N(rst),
         .Disp_Data(data),
         .state(current_state),
         .Sel(Sel),
         .DisPlay(DisPlay),
         .DisPlay1(DisPlay1)
    );
endmodule

数字系统/VS_verilog_源代码文件/verilog/lab4/tb.v
`timescale  1ns / 1ps
`include "top.v"


module tb_top;

// top Parameters
parameter PERIOD  = 10;


// top Inputs
reg   clk                                  = 0 ;
reg   rst                                  = 0 ;
reg   key0                                 = 0 ;
reg   key1                                 = 0 ;


// top Outputs
wire  [0:0]  unlock                        ;
wire  [7:0]Sel ;
wire   [7:0]DisPlay;
wire   [7:0]DisPlay1;

initial
begin
    forever #(PERIOD/2)  clk=~clk;
end



top  u_top (
    .clk                     ( clk                  ),
    .rst                     ( rst                  ),
    .key0                    ( key0                 ),
    .key1                    ( key1                 ),

 
    .unlock                  ( unlock         [0:0] ),
         .Sel(Sel [7:0]),
         .DisPlay(DisPlay[7:0]),
         .DisPlay1(DisPlay1[7:0])
);

initial
begin
    $dumpfile("tb_top.vcd");
    $dumpvars(0, tb_top);
    key0=0;
    key1=0;
    rst=0;
    #5
    rst=1;
    #10
    key1=1;
    #600
    key1=0;
    #100000
    key0=1;
    #600
    key0=0;
    #100000
    key0=1;
    #600
    key0=0;
    #100000
    key1=1;
    #600
    key1=0;
    #100000
    key0=1;
    #600
    key0=0;
    #100000
    $finish;
end

endmodule

数字系统/VS_verilog_源代码文件/verilog/lab4/tb_top.vcd
$date
	Tue May 09 19:10:46 2023
$end
$version
	Icarus Verilog
$end
$timescale
	1ps
$end
$scope module tb_top $end
$var wire 1 ! unlock $end
$var wire 8 " Sel [7:0] $end
$var wire 8 # DisPlay1 [7:0] $end
$var wire 8 $ DisPlay [7:0] $end
$var reg 1 % clk $end
$var reg 1 & key0 $end
$var reg 1 ' key1 $end
$var reg 1 ( rst $end
$scope module u_top $end
$var wire 1 % clk $end
$var wire 1 & key0 $end
$var wire 1 ' key1 $end
$var wire 1 ( rst $end
$var wire 1 ! unlock $end
$var wire 3 ) current_state [2:0] $end
$var wire 1 * b1 $end
$var wire 1 + b0 $end
$var wire 8 , Sel [7:0] $end
$var wire 8 - DisPlay1 [7:0] $end
$var wire 8 . DisPlay [7:0] $end
$var reg 32 / data [31:0] $end
$scope module u_FSM $end
$var wire 1 % clk $end
$var wire 3 0 debugstate [2:0] $end
$var wire 1 ( rst $end
$var wire 1 * b1 $end
$var wire 1 + b0 $end
$var reg 3 1 next_state [2:0] $end
$var reg 3 2 state [2:0] $end
$var reg 1 ! unlock $end
$upscope $end
$scope module u_Segment $end
$var wire 1 % Clk $end
$var wire 32 3 Disp_Data [31:0] $end
$var wire 1 ( Reset_N $end
$var wire 3 4 state [2:0] $end
$var reg 8 5 DisPlay [7:0] $end
$var reg 8 6 DisPlay1 [7:0] $end
$var reg 4 7 Disp_tmp [3:0] $end
$var reg 4 8 Disp_tmp1 [3:0] $end
$var reg 3 9 Num [2:0] $end
$var reg 8 : Sel [7:0] $end
$var reg 1 ; clk_1k $end
$var reg 16 < div_cnt [15:0] $end
$upscope $end
$scope module u_botton $end
$var wire 1 % clk $end
$var wire 1 & key $end
$var wire 1 = key_nedge $end
$var wire 1 ( rst_n $end
$var reg 20 > delay_cnt [19:0] $end
$var reg 1 ? delay_flag $end
$var reg 1 @ key_r0 $end
$var reg 1 A key_r1 $end
$var reg 1 + press $end
$upscope $end
$scope module u_botton1 $end
$var wire 1 % clk $end
$var wire 1 ' key $end
$var wire 1 B key_nedge $end
$var wire 1 ( rst_n $end
$var reg 20 C delay_cnt [19:0] $end
$var reg 1 D delay_flag $end
$var reg 1 E key_r0 $end
$var reg 1 F key_r1 $end
$var reg 1 * press $end
$upscope $end
$upscope $end
$upscope $end
$enddefinitions $end
#0
$dumpvars
1F
1E
0D
b0 C
0B
1A
1@
0?
b0 >
0=
b0 <
0;
bx :
b0 9
bx 8
bx 7
bx 6
bx 5
b0 4
bx 3
b0 2
b0 1
b0 0
bx /
bx .
bx -
bx ,
0+
0*
b0 )
0(
0'
0&
0%
bx $
bx #
bx "
0!
$end
#5000
b1 <
0E
0@
b0 /
b0 3
b0 "
b0 ,
b0 :
1(
1%
#10000
0%
#15000
1B
0A
0F
1E
b10 <
b111111 $
b111111 .
b111111 5
b0 7
1%
1'
#20000
0%
#25000
0B
b11 <
1D
1F
1%
#30000
0%
#35000
b1 C
b100 <
1%
#40000
0%
#45000
b101 <
b10 C
1%
#50000
0%
#55000
b11 C
b110 <
1%
#60000
0%
#65000
b111 <
b100 C
1%
#70000
0%
#75000
b101 C
b1000 <
1%
#80000
0%
#85000
b1001 <
b110 C
1%
#90000
0%
#95000
b111 C
b1010 <
1%
#100000
0%
#105000
b1011 <
b1000 C
1%
#110000
0%
#115000
b1001 C
b1100 <
1%
#120000
0%
#125000
b1101 <
b1010 C
1%
#130000
0%
#135000
b1011 C
b1110 <
1%
#140000
0%
#145000
b1111 <
b1100 C
1%
#150000
0%
#155000
b1101 C
b10000 <
1%
#160000
0%
#165000
b10001 <
b1110 C
1%
#170000
0%
#175000
b1111 C
b10010 <
1%
#180000
0%
#185000
b10011 <
b10000 C
1%
#190000
0%
#195000
b10001 C
b10100 <
1%
#200000
0%
#205000
b10101 <
b10010 C
1%
#210000
0%
#215000
b10011 C
b10110 <
1%
#220000
0%
#225000
b10111 <
b10100 C
1%
#230000
0%
#235000
b10101 C
b11000 <
1%
#240000
0%
#245000
b11001 <
b10110 C
1%
#250000
0%
#255000
b10111 C
b11010 <
1%
#260000
0%
#265000
b11011 <
b11000 C
1%
#270000
0%
#275000
b11001 C
b11100 <
1%
#280000
0%
#285000
b11101 <
b11010 C
1%
#290000
0%
#295000
b11011 C
b11110 <
1%
#300000
0%
#305000
b11111 <
b11100 C
1%
#310000
0%
#315000
b11101 C
b100000 <
1%
#320000
0%
#325000
b100001 <
b11110 C
1%
#330000
0%
#335000
b11111 C
b100010 <
1%
#340000
0%
#345000
b100011 <
b100000 C
1%
#350000
0%
#355000
b100001 C
b100100 <
1%
#360000
0%
#365000
b100101 <
b100010 C
1%
#370000
0%
#375000
b100011 C
b100110 <
1%
#380000
0%
#385000
b100111 <
b100100 C
1%
#390000
0%
#395000
b100101 C
b101000 <
1%
#400000
0%
#405000
b101001 <
b100110 C
1%
#410000
0%
#415000
b100111 C
b101010 <
1%
#420000
0%
#425000
b101011 <
b101000 C
1%
#430000
0%
#435000
b101001 C
b101100 <
1%
#440000
0%
#445000
b101101 <
b101010 C
1%
#450000
0%
#455000
b101011 C
b101110 <
1%
#460000
0%
#465000
b101111 <
b101100 C
1%
#470000
0%
#475000
b101101 C
b110000 <
1%
#480000
0%
#485000
b110001 <
b101110 C
1%
#490000
0%
#495000
b101111 C
b110010 <
1%
#500000
0%
#505000
b110011 <
b110000 C
1%
#510000
0%
#515000
b110001 C
b110100 <
1%
#520000
0%
#525000
b1 1
b110101 <
1*
0D
b0 C
1%
#530000
0%
#535000
0*
b1 )
b1 0
b1 4
b1 2
b110110 <
1%
#540000
0%
#545000
b110111 <
b1 /
b1 3
b1 "
b1 ,
b1 :
1%
#550000
0%
#555000
b111000 <
b110 $
b110 .
b110 5
b1 7
1%
#560000
0%
#565000
b111001 <
1%
#570000
0%
#575000
b111010 <
1%
#580000
0%
#585000
b111011 <
1%
#590000
0%
#595000
b111100 <
1%
#600000
0%
#605000
b111101 <
1%
#610000
0%
#615000
0E
b111110 <
1%
0'
#620000
0%
#625000
b111111 <
0F
1%
#630000
0%
#635000
b1000000 <
1%
#640000
0%
#645000
b1000001 <
1%
#650000
0%
#655000
b1000010 <
1%
#660000
0%
#665000
b1000011 <
1%
#670000
0%
#675000
b1000100 <
1%
#680000
0%
#685000
b1000101 <
1%
#690000
0%
#695000
b1000110 <
1%
#700000
0%
#705000
b1000111 <
1%
#710000
0%
#715000
b1001000 <
1%
#720000
0%
#725000
b1001001 <
1%
#730000
0%
#735000
b1001010 <
1%
#740000
0%
#745000
b1001011 <
1%
#750000
0%
#755000
b1001100 <
1%
#760000
0%
#765000
b1001101 <
1%
#770000
0%
#775000
b1001110 <
1%
#780000
0%
#785000
b1001111 <
1%
#790000
0%
#795000
b1010000 <
1%
#800000
0%
#805000
b1010001 <
1%
#810000
0%
#815000
b1010010 <
1%
#820000
0%
#825000
b1010011 <
1%
#830000
0%
#835000
b1010100 <
1%
#840000
0%
#845000
b1010101 <
1%
#850000
0%
#855000
b1010110 <
1%
#860000
0%
#865000
b1010111 <
1%
#870000
0%
#875000
b1011000 <
1%
#880000
0%
#885000
b1011001 <
1%
#890000
0%
#895000
b1011010 <
1%
#900000
0%
#905000
b1011011 <
1%
#910000
0%
#915000
b1011100 <
1%
#920000
0%
#925000
b1011101 <
1%
#930000
0%
#935000
b1011110 <
1%
#940000
0%
#945000
b1011111 <
1%
#950000
0%
#955000
b1100000 <
1%
#960000
0%
#965000
b1100001 <
1%
#970000
0%
#975000
b1100010 <
1%
#980000
0%
#985000
b1100011 <
1%
#990000
0%
#995000
b1100100 <
1%
#1000000
0%
#1005000
b1100101 <
1%
#1010000
0%
#1015000
b1100110 <
1%
#1020000
0%
#1025000
b1100111 <
1%
#1030000
0%
#1035000
b1101000 <
1%
#1040000
0%
#1045000
b1101001 <
1%
#1050000
0%
#1055000
b1101010 <
1%
#1060000
0%
#1065000
b1101011 <
1%
#1070000
0%
#1075000
b1101100 <
1%
#1080000
0%
#1085000
b1101101 <
1%
#1090000
0%
#1095000
b1101110 <
1%
#1100000
0%
#1105000
b1101111 <
1%
#1110000
0%
#1115000
b1110000 <
1%
#1120000
0%
#1125000
b1110001 <
1%
#1130000
0%
#1135000
b1110010 <
1%
#1140000
0%
#1145000
b1110011 <
1%
#1150000
0%
#1155000
b1110100 <
1%
#1160000
0%
#1165000
b1110101 <
1%
#1170000
0%
#1175000
b1110110 <
1%
#1180000
0%
#1185000
b1110111 <
1%
#1190000
0%
#1195000
b1111000 <
1%
#1200000
0%
#1205000
b1111001 <
1%
#1210000
0%
#1215000
b1111010 <
1%
#1220000
0%
#1225000
b1111011 <
1%
#1230000
0%
#1235000
b1111100 <
1%
#1240000
0%
#1245000
b1111101 <
1%
#1250000
0%
#1255000
b1111110 <
1%
#1260000
0%
#1265000
b1111111 <
1%
#1270000
0%
#1275000
b10000000 <
1%
#1280000
0%
#1285000
b10000001 <
1%
#1290000
0%
#1295000
b10000010 <
1%
#1300000
0%
#1305000
b10000011 <
1%
#1310000
0%
#1315000
b10000100 <
1%
#1320000
0%
#1325000
b10000101 <
1%
#1330000
0%
#1335000
b10000110 <
1%
#1340000
0%
#1345000
b10000111 <
1%
#1350000
0%
#1355000
b10001000 <
1%
#1360000
0%
#1365000
b10001001 <
1%
#1370000
0%
#1375000
b10001010 <
1%
#1380000
0%
#1385000
b10001011 <
1%
#1390000
0%
#1395000
b10001100 <
1%
#1400000
0%
#1405000
b10001101 <
1%
#1410000
0%
#1415000
b10001110 <
1%
#1420000
0%
#1425000
b10001111 <
1%
#1430000
0%
#1435000
b10010000 <
1%
#1440000
0%
#1445000
b10010001 <
1%
#1450000
0%
#1455000
b10010010 <
1%
#1460000
0%
#1465000
b10010011 <
1%
#1470000
0%
#1475000
b10010100 <
1%
#1480000
0%
#1485000
b10010101 <
1%
#1490000
0%
#1495000
b10010110 <
1%
#1500000
0%
#1505000
b10010111 <
1%
#1510000
0%
#1515000
b10011000 <
1%
#1520000
0%
#1525000
b10011001 <
1%
#1530000
0%
#1535000
b10011010 <
1%
#1540000
0%
#1545000
b10011011 <
1%
#1550000
0%
#1555000
b10011100 <
1%
#1560000
0%
#1565000
b10011101 <
1%
#1570000
0%
#1575000
b10011110 <
1%
#1580000
0%
#1585000
b10011111 <
1%
#1590000
0%
#1595000
b10100000 <
1%
#1600000
0%
#1605000
b10100001 <
1%
#1610000
0%
#1615000
b10100010 <
1%
#1620000
0%
#1625000
b10100011 <
1%
#1630000
0%
#1635000
b10100100 <
1%
#1640000
0%
#1645000
b10100101 <
1%
#1650000
0%
#1655000
b10100110 <
1%
#1660000
0%
#1665000
b10100111 <
1%
#1670000
0%
#1675000
b10101000 <
1%
#1680000
0%
#1685000
b10101001 <
1%
#1690000
0%
#1695000
b10101010 <
1%
#1700000
0%
#1705000
b10101011 <
1%
#1710000
0%
#1715000
b10101100 <
1%
#1720000
0%
#1725000
b10101101 <
1%
#1730000
0%
#1735000
b10101110 <
1%
#1740000
0%
#1745000
b10101111 <
1%
#1750000
0%
#1755000
b10110000 <
1%
#1760000
0%
#1765000
b10110001 <
1%
#1770000
0%
#1775000
b10110010 <
1%
#1780000
0%
#1785000
b10110011 <
1%
#1790000
0%
#1795000
b10110100 <
1%
#1800000
0%
#1805000
b10110101 <
1%
#1810000
0%
#1815000
b10110110 <
1%
#1820000
0%
#1825000
b10110111 <
1%
#1830000
0%
#1835000
b10111000 <
1%
#1840000
0%
#1845000
b10111001 <
1%
#1850000
0%
#1855000
b10111010 <
1%
#1860000
0%
#1865000
b10111011 <
1%
#1870000
0%
#1875000
b10111100 <
1%
#1880000
0%
#1885000
b10111101 <
1%
#1890000
0%
#1895000
b10111110 <
1%
#1900000
0%
#1905000
b10111111 <
1%
#1910000
0%
#1915000
b11000000 <
1%
#1920000
0%
#1925000
b11000001 <
1%
#1930000
0%
#1935000
b11000010 <
1%
#1940000
0%
#1945000
b11000011 <
1%
#1950000
0%
#1955000
b11000100 <
1%
#1960000
0%
#1965000
b11000101 <
1%
#1970000
0%
#1975000
b11000110 <
1%
#1980000
0%
#1985000
b11000111 <
1%
#1990000
0%
#1995000
b11001000 <
1%
#2000000
0%
#2005000
b11001001 <
1%
#2010000
0%
#2015000
b11001010 <
1%
#2020000
0%
#2025000
b11001011 <
1%
#2030000
0%
#2035000
b11001100 <
1%
#2040000
0%
#2045000
b11001101 <
1%
#2050000
0%
#2055000
b11001110 <
1%
#2060000
0%
#2065000
b11001111 <
1%
#2070000
0%
#2075000
b11010000 <
1%
#2080000
0%
#2085000
b11010001 <
1%
#2090000
0%
#2095000
b11010010 <
1%
#2100000
0%
#2105000
b11010011 <
1%
#2110000
0%
#2115000
b11010100 <
1%
#2120000
0%
#2125000
b11010101 <
1%
#2130000
0%
#2135000
b11010110 <
1%
#2140000
0%
#2145000
b11010111 <
1%
#2150000
0%
#2155000
b11011000 <
1%
#2160000
0%
#2165000
b11011001 <
1%
#2170000
0%
#2175000
b11011010 <
1%
#2180000
0%
#2185000
b11011011 <
1%
#2190000
0%
#2195000
b11011100 <
1%
#2200000
0%
#2205000
b11011101 <
1%
#2210000
0%
#2215000
b11011110 <
1%
#2220000
0%
#2225000
b11011111 <
1%
#2230000
0%
#2235000
b11100000 <
1%
#2240000
0%
#2245000
b11100001 <
1%
#2250000
0%
#2255000
b11100010 <
1%
#2260000
0%
#2265000
b11100011 <
1%
#2270000
0%
#2275000
b11100100 <
1%
#2280000
0%
#2285000
b11100101 <
1%
#2290000
0%
#2295000
b11100110 <
1%
#2300000
0%
#2305000
b11100111 <
1%
#2310000
0%
#2315000
b11101000 <
1%
#2320000
0%
#2325000
b11101001 <
1%
#2330000
0%
#2335000
b11101010 <
1%
#2340000
0%
#2345000
b11101011 <
1%
#2350000
0%
#2355000
b11101100 <
1%
#2360000
0%
#2365000
b11101101 <
1%
#2370000
0%
#2375000
b11101110 <
1%
#2380000
0%
#2385000
b11101111 <
1%
#2390000
0%
#2395000
b11110000 <
1%
#2400000
0%
#2405000
b11110001 <
1%
#2410000
0%
#2415000
b11110010 <
1%
#2420000
0%
#2425000
b11110011 <
1%
#2430000
0%
#2435000
b11110100 <
1%
#2440000
0%
#2445000
b11110101 <
1%
#2450000
0%
#2455000
b11110110 <
1%
#2460000
0%
#2465000
b11110111 <
1%
#2470000
0%
#2475000
b11111000 <
1%
#2480000
0%
#2485000
b11111001 <
1%
#2490000
0%
#2495000
b11111010 <
1%
#2500000
0%
#2505000
b11111011 <
1%
#2510000
0%
#2515000
b11111100 <
1%
#2520000
0%
#2525000
b11111101 <
1%
#2530000
0%
#2535000
b11111110 <
1%
#2540000
0%
#2545000
b11111111 <
1%
#2550000
0%
#2555000
b100000000 <
1%
#2560000
0%
#2565000
b100000001 <
1%
#2570000
0%
#2575000
b100000010 <
1%
#2580000
0%
#2585000
b100000011 <
1%
#2590000
0%
#2595000
b100000100 <
1%
#2600000
0%
#2605000
b100000101 <
1%
#2610000
0%
#2615000
b100000110 <
1%
#2620000
0%
#2625000
b100000111 <
1%
#2630000
0%
#2635000
b100001000 <
1%
#2640000
0%
#2645000
b100001001 <
1%
#2650000
0%
#2655000
b100001010 <
1%
#2660000
0%
#2665000
b100001011 <
1%
#2670000
0%
#2675000
b100001100 <
1%
#2680000
0%
#2685000
b100001101 <
1%
#2690000
0%
#2695000
b100001110 <
1%
#2700000
0%
#2705000
b100001111 <
1%
#2710000
0%
#2715000
b100010000 <
1%
#2720000
0%
#2725000
b100010001 <
1%
#2730000
0%
#2735000
b100010010 <
1%
#2740000
0%
#2745000
b100010011 <
1%
#2750000
0%
#2755000
b100010100 <
1%
#2760000
0%
#2765000
b100010101 <
1%
#2770000
0%
#2775000
b100010110 <
1%
#2780000
0%
#2785000
b100010111 <
1%
#2790000
0%
#2795000
b100011000 <
1%
#2800000
0%
#2805000
b100011001 <
1%
#2810000
0%
#2815000
b100011010 <
1%
#2820000
0%
#2825000
b100011011 <
1%
#2830000
0%
#2835000
b100011100 <
1%
#2840000
0%
#2845000
b100011101 <
1%
#2850000
0%
#2855000
b100011110 <
1%
#2860000
0%
#2865000
b100011111 <
1%
#2870000
0%
#2875000
b100100000 <
1%
#2880000
0%
#2885000
b100100001 <
1%
#2890000
0%
#2895000
b100100010 <
1%
#2900000
0%
#2905000
b100100011 <
1%
#2910000
0%
#2915000
b100100100 <
1%
#2920000
0%
#2925000
b100100101 <
1%
#2930000
0%
#2935000
b100100110 <
1%
#2940000
0%
#2945000
b100100111 <
1%
#2950000
0%
#2955000
b100101000 <
1%
#2960000
0%
#2965000
b100101001 <
1%
#2970000
0%
#2975000
b100101010 <
1%
#2980000
0%
#2985000
b100101011 <
1%
#2990000
0%
#2995000
b100101100 <
1%
#3000000
0%
#3005000
b100101101 <
1%
#3010000
0%
#3015000
b100101110 <
1%
#3020000
0%
#3025000
b100101111 <
1%
#3030000
0%
#3035000
b100110000 <
1%
#3040000
0%
#3045000
b100110001 <
1%
#3050000
0%
#3055000
b100110010 <
1%
#3060000
0%
#3065000
b100110011 <
1%
#3070000
0%
#3075000
b100110100 <
1%
#3080000
0%
#3085000
b100110101 <
1%
#3090000
0%
#3095000
b100110110 <
1%
#3100000
0%
#3105000
b100110111 <
1%
#3110000
0%
#3115000
b100111000 <
1%
#3120000
0%
#3125000
b100111001 <
1%
#3130000
0%
#3135000
b100111010 <
1%
#3140000
0%
#3145000
b100111011 <
1%
#3150000
0%
#3155000
b100111100 <
1%
#3160000
0%
#3165000
b100111101 <
1%
#3170000
0%
#3175000
b100111110 <
1%
#3180000
0%
#3185000
b100111111 <
1%
#3190000
0%
#3195000
b101000000 <
1%
#3200000
0%
#3205000
b101000001 <
1%
#3210000
0%
#3215000
b101000010 <
1%
#3220000
0%
#3225000
b101000011 <
1%
#3230000
0%
#3235000
b101000100 <
1%
#3240000
0%
#3245000
b101000101 <
1%
#3250000
0%
#3255000
b101000110 <
1%
#3260000
0%
#3265000
b101000111 <
1%
#3270000
0%
#3275000
b101001000 <
1%
#3280000
0%
#3285000
b101001001 <
1%
#3290000
0%
#3295000
b101001010 <
1%
#3300000
0%
#3305000
b101001011 <
1%
#3310000
0%
#3315000
b101001100 <
1%
#3320000
0%
#3325000
b101001101 <
1%
#3330000
0%
#3335000
b101001110 <
1%
#3340000
0%
#3345000
b101001111 <
1%
#3350000
0%
#3355000
b101010000 <
1%
#3360000
0%
#3365000
b101010001 <
1%
#3370000
0%
#3375000
b101010010 <
1%
#3380000
0%
#3385000
b101010011 <
1%
#3390000
0%
#3395000
b101010100 <
1%
#3400000
0%
#3405000
b101010101 <
1%
#3410000
0%
#3415000
b101010110 <
1%
#3420000
0%
#3425000
b101010111 <
1%
#3430000
0%
#3435000
b101011000 <
1%
#3440000
0%
#3445000
b101011001 <
1%
#3450000
0%
#3455000
b101011010 <
1%
#3460000
0%
#3465000
b101011011 <
1%
#3470000
0%
#3475000
b101011100 <
1%
#3480000
0%
#3485000
b101011101 <
1%
#3490000
0%
#3495000
b101011110 <
1%
