数字系统/VS_verilog_源代码文件/verilog/pid/pid_value.v
module pid_value (
	//system signals
	input		clk						, // 时钟信号
	input		rst_n					, // 复位信号，低电平有效
	input		signed [31:0]	  d_uk	    , // pid增量
	output	    reg signed [31:0]      uk0		  // pid输出值
);
 
reg signed [31:0] uk1 = 31'b0; // 上一时刻u(k-1)的值
always @ (d_uk) begin
	uk0 = uk1 + d_uk/1000; // 计算pid输出值
	uk1 = uk0;// 寄存上一时刻 u(k-1)的值    
end
endmodule

数字系统/VS_verilog_源代码文件/verilog/pid/incre_value.v
module  incre_value(
	input		signed [31:0]		  ek0	, // e(k)
	input		signed [31:0]		  ek1	, // e(k-1)
	input		signed [31:0]		  ek2	, // e(k-2)
	input		[15:0]		  kp	, // 比例系数
	input	    [15:0]		  ki	, // 积分系数
	input		[15:0]		  kd	, // 微分系数
	output		signed [31:0]		 d_uk	  // pid增量
);
 
assign  d_uk = kp*(ek0 -ek1) + ki*ek0 + kd*((ek0 - ek1)-(ek1 - ek2)); // 计算pid增量
 
endmodule

数字系统/VS_verilog_源代码文件/verilog/pid/error.v
module  error(
	//system signals
	input		clk						, // 时钟信号
	input		rst_n					, // 复位信号，低电平有效
	input		signed [31:0]		target	, // 目标值
	input		signed [31:0]		   y	, // 实际输出值
	output		signed [31:0]		  ek0	, // e(k)
	output		reg	 signed [31:0]		  ek1	, // e(k-1)
	output		reg	 signed [31:0]		  ek2	  // e(k-2)
);
 
assign ek0 = target - y; // 计算e(k)
 
always @ (posedge clk or negedge rst_n) begin
	if(!rst_n) begin // 初始化误差值
		ek1 <= 32'b0;
		ek2 <= 32'b0;
	end 	
	else begin
		ek1 <= ek0; // 延时一个时钟周期，得到e(k-1)
        ek2 <= ek1; // 再延时一个时钟周期，得到e(k-2) 
	end	   
end
endmodule

数字系统/VS_verilog_源代码文件/verilog/pid/demo_top.v
`include "error.v"
`include "incre_value.v"
`include "pid_value.v"
module  demo_top(
	//system signals
	input		clk						, // 时钟信号
	input		rst_n					, // 复位信号，低电平有效
	input		signed [31:0]		target	, // 目标值
	input		signed [31:0]		   y	, // 实际输出值
	input		[15:0]		  kp	, // 比例系数
	input		[15:0]		  ki	, // 积分系数
	input		[15:0]		  kd	, // 微分系数
	output		signed [31:0]	      uk0	  // pid输出值
);
 
wire	signed [31:0] ek0; // e(k)
wire	signed [31:0] ek1; // e(k-1)
wire	signed [31:0] ek2; // e(k-2)
error error_demo(.clk(clk),
				 .rst_n(rst_n),
				 .target(target),
				 .y(y),
				 .ek0(ek0),
				 .ek1(ek1),
				 .ek2(ek2)
	            );
 
 
wire signed [31:0] d_uk;// pid增量
incre_value incre_value_demo(.ek0(ek0),
							 .ek1(ek1),
							 .ek2(ek2),
							 .kp(kp),
							 .ki(ki),
							 .kd(kd),
							 .d_uk(d_uk)
				             );
 
pid_value pid_value_demo(.clk(clk),
						 .rst_n(rst_n),
						 .d_uk(d_uk),
						 .uk0(uk0)
				        );
 
endmodule

数字系统/VS_verilog_源代码文件/verilog/pid/pid_tb.v
//~ `New testbench
`include "demo_top.v"

`timescale  1ns / 1ps

module tb_demo_top;

// demo_top Parameters
parameter PERIOD  = 10;


// demo_top Inputs
reg   clk                                  = 0 ;
reg   rst_n                                = 0 ;
reg   [31:0]  target                        = 0 ;
reg   [31:0]  y                             = 0 ;
reg   [15:0]  kp                            = 0 ;
reg   [15:0]  ki                            = 0 ;
reg   [15:0]  kd                            = 0 ;

// demo_top Outputs
wire  [31:0]  uk0                          ;



demo_top  u_demo_top (
    .clk                     ( clk            ),
    .rst_n                   ( rst_n          ),
    .target                  ( target  [31:0]  ),
    .y                       ( y       [31:0]  ),
    .kp                      ( kp      [15:0]  ),
    .ki                      ( ki      [15:0]  ),
    .kd                      ( kd      [15:0]  ),
    .uk0                     ( uk0     [31:0] )
);

parameter clk_period = 10;  
initial  
    clk = 0;  
always #(clk_period/2) clk = ~clk;  
// always @(negedge clk) begin
//     y=y+uk0;
// end



initial
begin
    $dumpfile("demo_top.vcd");
    $dumpvars(0, tb_demo_top);
    clk   = 0;
    target = 10000000;
    y      = 0;
    kp     = 700;
    kd     = 0;
    ki     = 0;

    #10;
    y=uk0;
    #10;
    y=uk0;
    #10;
    y=uk0;
    #10;
    y=uk0;
    #10;
    y=uk0;
    #10;
    y=uk0;
    #10;
    #10;
    y=uk0;
    #10;
    y=uk0;
    #10;
    y=uk0;
    #10;
    y=uk0;
    #10;
    y=uk0;
    #10;
    y=uk0;
    #10;


    
    $finish;
end

endmodule

数字系统/VS_verilog_源代码文件/verilog/pid/demo_top.vcd
$date
	Sun Apr 30 21:30:42 2023
$end
$version
	Icarus Verilog
$end
$timescale
	1ps
$end
$scope module tb_demo_top $end
$var wire 32 ! uk0 [31:0] $end
$var reg 1 " clk $end
$var reg 16 # kd [15:0] $end
$var reg 16 $ ki [15:0] $end
$var reg 16 % kp [15:0] $end
$var reg 1 & rst_n $end
$var reg 32 ' target [31:0] $end
$var reg 32 ( y [31:0] $end
$scope module u_demo_top $end
$var wire 1 " clk $end
$var wire 16 ) kd [15:0] $end
$var wire 16 * ki [15:0] $end
$var wire 16 + kp [15:0] $end
$var wire 1 & rst_n $end
$var wire 32 , target [31:0] $end
$var wire 32 - y [31:0] $end
$var wire 32 . uk0 [31:0] $end
$var wire 32 / ek2 [31:0] $end
$var wire 32 0 ek1 [31:0] $end
$var wire 32 1 ek0 [31:0] $end
$var wire 32 2 d_uk [31:0] $end
$scope module error_demo $end
$var wire 1 " clk $end
$var wire 1 & rst_n $end
$var wire 32 3 target [31:0] $end
$var wire 32 4 y [31:0] $end
$var wire 32 5 ek0 [31:0] $end
$var reg 32 6 ek1 [31:0] $end
$var reg 32 7 ek2 [31:0] $end
$upscope $end
$scope module incre_value_demo $end
$var wire 32 8 ek0 [31:0] $end
$var wire 32 9 ek1 [31:0] $end
$var wire 32 : ek2 [31:0] $end
$var wire 16 ; kd [15:0] $end
$var wire 16 < ki [15:0] $end
$var wire 16 = kp [15:0] $end
$var wire 32 > d_uk [31:0] $end
$upscope $end
$scope module pid_value_demo $end
$var wire 1 " clk $end
$var wire 32 ? d_uk [31:0] $end
$var wire 1 & rst_n $end
$var reg 32 @ uk0 [31:0] $end
$var reg 32 A uk1 [31:0] $end
$upscope $end
$upscope $end
$upscope $end
$enddefinitions $end
#0
$dumpvars
b11111111111001111011110101010010 A
b11111111111001111011110101010010 @
b10100001001110111000011000000000 ?
b10100001001110111000011000000000 >
b1010111100 =
b0 <
b0 ;
b0 :
b0 9
b100110001001011010000000 8
b0 7
b0 6
b100110001001011010000000 5
b0 4
b100110001001011010000000 3
b10100001001110111000011000000000 2
b100110001001011010000000 1
b0 0
b0 /
b11111111111001111011110101010010 .
b0 -
b100110001001011010000000 ,
b1010111100 +
b0 *
b0 )
b0 (
b100110001001011010000000 '
0&
b1010111100 %
b0 $
b0 #
0"
b11111111111001111011110101010010 !
$end
#5000
1"
#10000
b11111111111000000111011000011110 A
b11111111111000000111011000011110 !
b11111111111000000111011000011110 .
b11111111111000000111011000011110 @
0"
b11100011100100011101100111001000 2
b11100011100100011101100111001000 >
b11100011100100011101100111001000 ?
b101100001101100100101110 1
b101100001101100100101110 5
b101100001101100100101110 8
b11111111111001111011110101010010 (
b11111111111001111011110101010010 -
b11111111111001111011110101010010 4
#15000
1"
#20000
b11111111110111100100011100101000 A
b11111111110111100100011100101000 !
b11111111110111100100011100101000 .
b11111111110111100100011100101000 @
0"
b11110111011110001000101111111000 2
b11110111011110001000101111111000 >
b11110111011110001000101111111000 ?
b101110000010000001100010 1
b101110000010000001100010 5
b101110000010000001100010 8
b11111111111000000111011000011110 (
b11111111111000000111011000011110 -
b11111111111000000111011000011110 4
#25000
1"
#30000
b11111111110111011001111101111000 A
b11111111110111011001111101111000 !
b11111111110111011001111101111000 .
b11111111110111011001111101111000 @
0"
b11111101011100001111010010100000 2
b11111101011100001111010010100000 >
b11111101011100001111010010100000 ?
b101110100100111101011000 1
b101110100100111101011000 5
b101110100100111101011000 8
b11111111110111100100011100101000 (
b11111111110111100100011100101000 -
b11111111110111100100011100101000 4
#35000
1"
#40000
b11111111110111010110110100101001 A
b11111111110111010110110100101001 !
b11111111110111010110110100101001 .
b11111111110111010110110100101001 @
0"
b11111111001110110111100111100000 2
b11111111001110110111100111100000 >
b11111111001110110111100111100000 ?
b101110101111011100001000 1
b101110101111011100001000 5
b101110101111011100001000 8
b11111111110111011001111101111000 (
b11111111110111011001111101111000 -
b11111111110111011001111101111000 4
#45000
1"
#50000
b11111111110111010101111000010001 A
b11111111110111010101111000010001 !
b11111111110111010101111000010001 .
b11111111110111010101111000010001 @
0"
b11111111110001010000100111100100 2
b11111111110001010000100111100100 >
b11111111110001010000100111100100 ?
b101110110010100101010111 1
b101110110010100101010111 5
b101110110010100101010111 8
b11111111110111010110110100101001 (
b11111111110111010110110100101001 -
b11111111110111010110110100101001 4
#55000
1"
#60000
b11111111110111010101100110001010 A
b11111111110111010101100110001010 !
b11111111110111010101100110001010 .
b11111111110111010101100110001010 @
0"
b11111111111011100100111110000100 2
b11111111111011100100111110000100 >
b11111111111011100100111110000100 ?
b101110110011100001101111 1
b101110110011100001101111 5
b101110110011100001101111 8
b11111111110111010101111000010001 (
b11111111110111010101111000010001 -
b11111111110111010101111000010001 4
#65000
1"
#70000
0"
#75000
1"
#80000
b11111111110111010101100000101111 A
b11111111110111010101100000101111 !
b11111111110111010101100000101111 .
b11111111110111010101100000101111 @
0"
b11111111111110101011000010101000 2
b11111111111110101011000010101000 >
b11111111111110101011000010101000 ?
b101110110011110011110110 1
b101110110011110011110110 5
b101110110011110011110110 8
b11111111110111010101100110001010 (
b11111111110111010101100110001010 -
b11111111110111010101100110001010 4
#85000
1"
#90000
b11111111110111010101011111000110 A
b11111111110111010101011111000110 !
b11111111110111010101011111000110 .
b11111111110111010101011111000110 @
0"
b11111111111111100110010101111100 2
b11111111111111100110010101111100 >
b11111111111111100110010101111100 ?
b101110110011111001010001 1
b101110110011111001010001 5
b101110110011111001010001 8
b11111111110111010101100000101111 (
b11111111110111010101100000101111 -
b11111111110111010101100000101111 4
#95000
1"
#100000
b11111111110111010101011110100111 A
b11111111110111010101011110100111 !
b11111111110111010101011110100111 .
b11111111110111010101011110100111 @
0"
b11111111111111111000010010011000 2
b11111111111111111000010010011000 >
b11111111111111111000010010011000 ?
b101110110011111010111010 1
b101110110011111010111010 5
b101110110011111010111010 8
b11111111110111010101011111000110 (
b11111111110111010101011111000110 -
b11111111110111010101011111000110 4
#105000
1"
#110000
b11111111110111010101011110011110 A
b11111111110111010101011110011110 !
b11111111110111010101011110011110 .
b11111111110111010101011110011110 @
0"
b11111111111111111101100101011100 2
b11111111111111111101100101011100 >
b11111111111111111101100101011100 ?
b101110110011111011011001 1
b101110110011111011011001 5
b101110110011111011011001 8
b11111111110111010101011110100111 (
b11111111110111010101011110100111 -
b11111111110111010101011110100111 4
#115000
1"
#120000
b11111111110111010101011110011011 A
b11111111110111010101011110011011 !
b11111111110111010101011110011011 .
b11111111110111010101011110011011 @
0"
b11111111111111111111000111111000 2
b11111111111111111111000111111000 >
b11111111111111111111000111111000 ?
b101110110011111011100010 1
b101110110011111011100010 5
b101110110011111011100010 8
b11111111110111010101011110011110 (
b11111111110111010101011110011110 -
b11111111110111010101011110011110 4
#125000
1"
#130000
b11111111110111010101011110011010 A
b11111111110111010101011110011010 !
b11111111110111010101011110011010 .
b11111111110111010101011110011010 @
0"
b11111111111111111111101000101100 2
b11111111111111111111101000101100 >
b11111111111111111111101000101100 ?
b101110110011111011100101 1
b101110110011111011100101 5
b101110110011111011100101 8
b11111111110111010101011110011011 (
b11111111110111010101011110011011 -
b11111111110111010101011110011011 4
