数字系统/VS_verilog_源代码文件/verilog/botton/key_driver.v
module key_driver(
	
	input		wire				clk			,
	input		wire				rst_n		,
	input		wire				en			,
	
	output		reg		[3:0]		led_o		
	
	);
	
	always @(posedge clk or negedge rst_n) begin
		if(!rst_n) begin
			led_o <= 0;
		end
		else if(en) begin
			//按下的信号出现，则LED灯变化
			//将低一位移置高位并进行拼接
			led_o <= {~led_o[0], led_o[3:1]};
		end	
	end
	
endmodule

数字系统/VS_verilog_源代码文件/verilog/botton/key_debounce.v
module key_debounce(
		input 	wire		clk		,		//50MHz时钟频率
		input 	wire		rst_n	,		//复位按键
		input 	wire		key		,		//按键输入口
		output 	reg 		press			//按键按下标志输出
	);
	
	//全局参数定义
	parameter	DELAY_TIME = 1000000;	//延时20ms也就是1000_000个时钟周期
	
	//信号定义
	reg				key_r0		;		//同步 当前时钟周期输入状态
	reg				key_r1		;		//打拍 前一个时钟周期输入的状态
	wire			key_nedge	;		//下降沿
	
	reg		[19:0]	delay_cnt	;		//计数20ms，需要20ms/20ns = 1000_000个时钟周期
	reg				delay_flag	;		//按下的下降沿标志
	initial begin
		delay_cnt=0;
	end
	//同步计数实现
	always @(posedge clk or negedge rst_n) begin
		if(rst_n == 1'b0) begin
			key_r0 <= 1'b1;
			key_r1 <= 1'b1;
		end
		else begin
			key_r0 <= key;
			key_r1 <= key_r0;
		end
	end
	
	assign key_nedge = key_r0 & ~key_r1;	//检测下降沿
	//assign key_pedge = key_r0 & ~key_r1;	//检测上升沿
	
	//delay_cnt 计数器计满1000_000个时钟周期
	always @(posedge clk or negedge rst_n) begin
		if(!rst_n) begin
			delay_cnt <= 0;
		end
		else if(delay_flag) begin
			//按下的下降沿标志出现，则执行
			if(delay_cnt == DELAY_TIME - 1) begin
				//如果计满1000_000个时钟周期，则归零处理
				delay_cnt <= 0;
			end
			else begin
				//没有计满，则不断累加
				delay_cnt <= delay_cnt + 1;
			end
		end
	end
	
	//delay_flag
	always @(posedge clk or negedge rst_n) begin
		if(!rst_n) begin
			delay_flag <= 1'b0;
		end
		else if(key_nedge) begin
			//下降沿出现后，设置按下标志位为 1
			delay_flag <= 1'b1;
		end
		else if(delay_cnt == DELAY_TIME - 1) begin
			/*
			计数器计满1000_000个时钟周期后，
			设置按下标志位为 0
			表示按键按下结束，以备下次按键
			*/
			delay_flag <= 1'b0;
		end
	end
	
	//press
	always @(posedge clk or negedge rst_n) begin
		if(!rst_n) begin
			press <= 1'b0;
		end
		else if(delay_cnt == DELAY_TIME - 1) begin
			/*
			计满1000_000个时钟周期后
			获取当前的按压标志
			此时 press = 1
			*/
			press <= key_r0;
			// 上升沿时press<=key_r0;
		end
		else begin
			/*
			没有计满1000_000个时钟周期
			则 press = 0
			*/
			press <= 1'b0;
		end
	end

endmodule

数字系统/VS_verilog_源代码文件/verilog/botton/key_led.v
`include "key_debounce.v"
`include "key_driver.v"

module key_led(
	input						clk			,		//系统时钟
	input 						rst_n		,		//复位 低电平有效
	
	input		wire			key_in		,		//顶层模块定义wire型
	output 		wire	[3:0]	led				//输出led信号
	);

	wire 		press		;						//定义一条线，连接按键按下标志信号

	//模块例化
	key_debounce u_key_debounce(
		.clk			(clk	),
		.rst_n			(rst_n	),
		.key			(key_in	),
		.press			(press	)			//按键按下标志
	);
	
	key_driver u_key_driver(
		.clk			(clk	),
		.rst_n			(rst_n	),
		.en				(press	),
		.led_o			(led	)
	);

endmodule

数字系统/VS_verilog_源代码文件/verilog/botton/tb.v
`timescale  1ns / 1ps
`include "key_led.v"

module tb_key_led;

// key_led Parameters
parameter PERIOD  = 20;


// key_led Inputs
reg   clk                                  = 0 ;
reg   rst_n                                = 0 ;
reg   key_in                               = 0 ;

// key_led Outputs
wire  [3:0]  led                           ;


initial
begin
    forever #(PERIOD/2)  clk=~clk;
end

key_led  u_key_led (
    .clk                     ( clk           ),
    .rst_n                   ( rst_n         ),
    .key_in                  ( key_in        ),

    .led                     ( led     [3:0] )
);


initial
begin
    $dumpfile("tb_key_led.vcd");
    $dumpvars(0, tb_key_led);
    rst_n = 0;
    #10
    rst_n=1;
    key_in=0;
    #1000
    key_in=1;
    #10
    key_in=0;
    #5
    key_in=1;
    #7
    key_in=0;
        #5
    key_in=1;
    #7
    key_in=0;
        #5
    key_in=1;
    #7
    key_in=0;
    #10
    key_in=1;
    #50000;
    key_in=0;
    #100000;
    $finish;
end

endmodule

数字系统/VS_verilog_源代码文件/verilog/botton/tb_key_led.vcd
$date
	Fri May 05 12:01:29 2023
$end
$version
	Icarus Verilog
$end
$timescale
	1ps
$end
$scope module tb_key_led $end
$var wire 4 ! led [3:0] $end
$var reg 1 " clk $end
$var reg 1 # key_in $end
$var reg 1 $ rst_n $end
$scope module u_key_led $end
$var wire 1 " clk $end
$var wire 1 # key_in $end
$var wire 1 $ rst_n $end
$var wire 1 % press $end
$var wire 4 & led [3:0] $end
$scope module u_key_debounce $end
$var wire 1 " clk $end
$var wire 1 # key $end
$var wire 1 ' key_nedge $end
$var wire 1 $ rst_n $end
$var reg 20 ( delay_cnt [19:0] $end
$var reg 1 ) delay_flag $end
$var reg 1 * key_r0 $end
$var reg 1 + key_r1 $end
$var reg 1 % press $end
$upscope $end
$scope module u_key_driver $end
$var wire 1 " clk $end
$var wire 1 % en $end
$var wire 1 $ rst_n $end
$var reg 4 , led_o [3:0] $end
$upscope $end
$upscope $end
$upscope $end
$enddefinitions $end
#0
$dumpvars
b0 ,
1+
1*
0)
b0 (
0'
b0 &
0%
0$
0#
0"
b0 !
$end
#10000
0*
1$
1"
#20000
0"
#30000
0+
1"
#40000
0"
#50000
1"
#60000
0"
#70000
1"
#80000
0"
#90000
1"
#100000
0"
#110000
1"
#120000
0"
#130000
1"
#140000
0"
#150000
1"
#160000
0"
#170000
1"
#180000
0"
#190000
1"
#200000
0"
#210000
1"
#220000
0"
#230000
1"
#240000
0"
#250000
1"
#260000
0"
#270000
1"
#280000
0"
#290000
1"
#300000
0"
#310000
1"
#320000
0"
#330000
1"
#340000
0"
#350000
1"
#360000
0"
#370000
1"
#380000
0"
#390000
1"
#400000
0"
#410000
1"
#420000
0"
#430000
1"
#440000
0"
#450000
1"
#460000
0"
#470000
1"
#480000
0"
#490000
1"
#500000
0"
#510000
1"
#520000
0"
#530000
1"
#540000
0"
#550000
1"
#560000
0"
#570000
1"
#580000
0"
#590000
1"
#600000
0"
#610000
1"
#620000
0"
#630000
1"
#640000
0"
#650000
1"
#660000
0"
#670000
1"
#680000
0"
#690000
1"
#700000
0"
#710000
1"
#720000
0"
#730000
1"
#740000
0"
#750000
1"
#760000
0"
#770000
1"
#780000
0"
#790000
1"
#800000
0"
#810000
1"
#820000
0"
#830000
1"
#840000
0"
#850000
1"
#860000
0"
#870000
1"
#880000
0"
#890000
1"
#900000
0"
#910000
1"
#920000
0"
#930000
1"
#940000
0"
#950000
1"
#960000
0"
#970000
1"
#980000
0"
#990000
1"
#1000000
0"
#1010000
1'
1*
1"
1#
#1020000
0"
0#
#1025000
1#
#1030000
0'
1+
1)
1"
#1032000
0#
#1037000
1#
#1040000
0"
#1044000
0#
#1049000
1#
#1050000
b1 (
1"
#1056000
0#
#1060000
0"
#1066000
1#
#1070000
b10 (
1"
#1080000
0"
#1090000
b11 (
1"
#1100000
0"
#1110000
b100 (
1"
#1120000
0"
#1130000
b101 (
1"
#1140000
0"
#1150000
b110 (
1"
#1160000
0"
#1170000
b111 (
1"
#1180000
0"
#1190000
b1000 (
1"
#1200000
0"
#1210000
b1001 (
1"
#1220000
0"
#1230000
b1010 (
1"
#1240000
0"
#1250000
b1011 (
1"
#1260000
0"
#1270000
b1100 (
1"
#1280000
0"
#1290000
b1101 (
1"
#1300000
0"
#1310000
b1110 (
1"
#1320000
0"
#1330000
b1111 (
1"
#1340000
0"
#1350000
b10000 (
1"
#1360000
0"
#1370000
b10001 (
1"
#1380000
0"
#1390000
b10010 (
1"
#1400000
0"
#1410000
b10011 (
1"
#1420000
0"
#1430000
b10100 (
1"
#1440000
0"
#1450000
b10101 (
1"
#1460000
0"
#1470000
b10110 (
1"
#1480000
0"
#1490000
b10111 (
1"
#1500000
0"
#1510000
b11000 (
1"
#1520000
0"
#1530000
b11001 (
1"
#1540000
0"
#1550000
b11010 (
1"
#1560000
0"
#1570000
b11011 (
1"
#1580000
0"
#1590000
b11100 (
1"
#1600000
0"
#1610000
b11101 (
1"
#1620000
0"
#1630000
b11110 (
1"
#1640000
0"
#1650000
b11111 (
1"
#1660000
0"
#1670000
b100000 (
1"
#1680000
0"
#1690000
b100001 (
1"
#1700000
0"
#1710000
b100010 (
1"
#1720000
0"
#1730000
b100011 (
1"
#1740000
0"
#1750000
b100100 (
1"
#1760000
0"
#1770000
b100101 (
1"
#1780000
0"
#1790000
b100110 (
1"
#1800000
0"
#1810000
b100111 (
1"
#1820000
0"
#1830000
b101000 (
1"
#1840000
0"
#1850000
b101001 (
1"
#1860000
0"
#1870000
b101010 (
1"
#1880000
0"
#1890000
b101011 (
1"
#1900000
0"
#1910000
b101100 (
1"
#1920000
0"
#1930000
b101101 (
1"
#1940000
0"
#1950000
b101110 (
1"
#1960000
0"
#1970000
b101111 (
1"
#1980000
0"
#1990000
b110000 (
1"
#2000000
0"
#2010000
b110001 (
1"
#2020000
0"
#2030000
b0 (
0)
1%
1"
#2040000
0"
#2050000
b1000 !
b1000 &
b1000 ,
0%
1"
