数字系统/VS_verilog_源代码文件/homework6/uart_rx.v
module uart_rx (
    input clk,
    input rxd,
    output  data_rdy,  // goes high when there is a new byte available
    output  [7:0] data  
);

localparam IDLE = 0;
localparam RECEIVING = 1;
localparam DONE = 2;

reg [2:0] state=0, next_state=0; 
reg [2:0] count;
reg [7:0] rx_data=0;
reg rx_data_rdy;

always @(posedge clk ) begin
    state <= next_state;
end
always @(*) begin
    next_state = state;
    case (state)
        IDLE: begin
            if (rxd == 0) begin
                next_state = RECEIVING;
            end
        end
        RECEIVING: begin
            if (count == 7) begin
                next_state = DONE;
            end else begin
                next_state = RECEIVING;
            end
        end
        DONE: begin
            next_state = IDLE;
        end
    endcase
end
    
always @(posedge clk ) begin
    if (state == IDLE) begin
        count <= 0;
    end else if (state == RECEIVING) begin
        count <= count + 1;
    end else if (state == DONE) begin
        count <= 0;
    end
end
always @(posedge clk ) begin
    if (state == RECEIVING) begin
        rx_data[count] <= rxd;
    end 

    end
assign data_rdy = (state == DONE);  //
assign data = rx_data;  //


endmodule

数字系统/VS_verilog_源代码文件/homework6/uart_tx.v
module uart_tx (
    input clk,
    input [7:0] tx_data,
    input tx_start,
    output tx_busy,
    output reg txd
);
    localparam IDLE = 0;
    localparam START = 1;
    localparam SENDING = 2;
    localparam DONE = 3;
    reg [2:0] state=IDLE, next_state=IDLE; 
    reg [2:0] count;


    always @(posedge clk ) begin
        state <= next_state;
    end    
    always @(*) begin
        next_state = state;
        case (state)
            IDLE: begin
                if (tx_start) begin
                    next_state = START;
                end
            end
            START: begin
                next_state = SENDING;
            end
            SENDING: begin
                if (count == 7) begin
                    next_state = DONE;
                end else begin
                    next_state = SENDING;
                end
            end
            DONE: begin
                next_state = IDLE;
            end
        endcase
    end
    always @(posedge clk ) begin
        if (state == SENDING) begin
            count <= count + 1;
        end else if (state == DONE||state == IDLE) begin
            count <= 0;
        end
        end
    always @(posedge clk ) begin
        if (state == START) begin
            txd <= 0;
        end else if (state == SENDING) begin
            txd <= tx_data[count];
        end else if (state == DONE|state==IDLE) begin
            txd <= 1;
        end
        end
    assign tx_busy = (state == SENDING);  
endmodule

数字系统/VS_verilog_源代码文件/homework6/top.v
`include "uart_tx.v"
`include "uart_rx.v"
module top (
    input clk,
    input rxd,
    output txd
);

    wire [7:0] data;   
    wire dete_busy;
    uart_tx  u_uart_tx (
        .clk                     ( clk             ),
        .tx_data                 ( data      [7:0] ),
        .tx_start                ( dete_rdy        ),
        .tx_busy                 ( dete_busy       ),
        .txd                     ( txd             )
    );
    uart_rx  u_uart_rx (
        .clk                     ( clk             ),
        .rxd                     ( rxd             ),
        .data_rdy                ( dete_rdy        ),
        .data                    ( data      [7:0] )
    );
        
endmodule

数字系统/VS_verilog_源代码文件/homework6/top_tb.v
//~ `New testbench
`include "top.v"
`timescale  1ns / 1ps
module tb_top;
// top Parameters
parameter PERIOD  = 10;
// top Inputs
reg   clk                                  = 0 ;
reg   rxd                                  = 0 ;
// top Outputs
wire  txd                                  ;
initial
begin
    forever #(PERIOD/2)  clk=~clk;
end
top  u_top (
    .clk                     ( clk   ),
    .rxd                     ( rxd   ),
    .txd                     ( txd   )
);
initial
begin
     $dumpfile("tb_top.vcd");
        $dumpvars(0,tb_top);
    rxd = 1;
    #100
    rxd = 0;
    #10
    rxd = 1;
    #10
    rxd = 0;
    #10
    rxd = 1;
    #10
    rxd = 0;
    #10
    rxd = 0;
    #10
    rxd = 1;
    #10
    rxd = 1;
    #10
    rxd = 0;
    #10
    rxd = 1;
    #200
    $finish;
end

endmodule

数字系统/VS_verilog_源代码文件/homework6/tb_top.vcd
$date
	Sat May 27 23:49:04 2023
$end
$version
	Icarus Verilog
$end
$timescale
	1ps
$end
$scope module tb_top $end
$var wire 1 ! txd $end
$var reg 1 " clk $end
$var reg 1 # rxd $end
$scope module u_top $end
$var wire 1 " clk $end
$var wire 1 # rxd $end
$var wire 1 ! txd $end
$var wire 1 $ dete_rdy $end
$var wire 1 % dete_busy $end
$var wire 8 & data [7:0] $end
$scope module u_uart_rx $end
$var wire 1 " clk $end
$var wire 8 ' data [7:0] $end
$var wire 1 # rxd $end
$var wire 1 $ data_rdy $end
$var reg 3 ( count [2:0] $end
$var reg 3 ) next_state [2:0] $end
$var reg 8 * rx_data [7:0] $end
$var reg 3 + state [2:0] $end
$upscope $end
$scope module u_uart_tx $end
$var wire 1 " clk $end
$var wire 8 , tx_data [7:0] $end
$var wire 1 $ tx_start $end
$var wire 1 % tx_busy $end
$var reg 3 - count [2:0] $end
$var reg 3 . next_state [2:0] $end
$var reg 3 / state [2:0] $end
$var reg 1 ! txd $end
$upscope $end
$upscope $end
$upscope $end
$enddefinitions $end
#0
$dumpvars
b0 /
b0 .
bx -
b0 ,
b0 +
b0 *
b0 )
bx (
b0 '
b0 &
0%
0$
1#
0"
x!
$end
#5000
b0 -
1!
b0 (
1"
#10000
0"
#15000
1"
#20000
0"
#25000
1"
#30000
0"
#35000
1"
#40000
0"
#45000
1"
#50000
0"
#55000
1"
#60000
0"
#65000
1"
#70000
0"
#75000
1"
#80000
0"
#85000
1"
#90000
0"
#95000
1"
#100000
b1 )
0"
0#
#105000
b1 +
1"
#110000
0"
1#
#115000
b1 &
b1 '
b1 ,
b1 *
b1 (
1"
#120000
0"
0#
#125000
b10 (
1"
#130000
0"
1#
#135000
b101 &
b101 '
b101 ,
b101 *
b11 (
1"
#140000
0"
0#
#145000
b100 (
1"
#150000
0"
#155000
b101 (
1"
#160000
0"
1#
#165000
b110 (
b100101 &
b100101 '
b100101 ,
b100101 *
1"
#170000
0"
#175000
b10 )
b1100101 &
b1100101 '
b1100101 ,
b1100101 *
b111 (
1"
#180000
b10 )
0"
0#
#185000
b1 .
b0 )
1$
b10 +
b0 (
1"
#190000
b0 )
0"
1#
#195000
b10 .
0$
b0 +
b1 /
1"
#200000
0"
#205000
1%
b10 /
0!
1"
#210000
0"
#215000
1!
b1 -
1"
#220000
0"
#225000
b10 -
0!
1"
#230000
0"
#235000
1!
b11 -
1"
#240000
0"
#245000
b100 -
0!
1"
#250000
0"
#255000
b101 -
1"
#260000
0"
#265000
b110 -
1!
1"
#270000
0"
#275000
b11 .
b111 -
1"
#280000
0"
#285000
b0 .
0%
b11 /
b0 -
0!
1"
#290000
0"
#295000
1!
b0 /
1"
