数字系统/VS_verilog_源代码文件/homework6/uart_tx.v
module uart_tx (
    input clk,
    input [7:0] tx_data,
    input tx_start,
    output tx_busy,
    output reg txd
);
    localparam IDLE = 0;
    localparam START = 1;
    localparam SENDING = 2;
    localparam DONE = 3;
    reg [2:0] state=IDLE, next_state=IDLE; 
    reg [2:0] count;


    always @(posedge clk ) begin
        state <= next_state;
    end    
    always @(*) begin
        next_state = state;
        case (state)
            IDLE: begin
                if (tx_start) begin
                    next_state = START;
                end
            end
            START: begin
                next_state = SENDING;
            end
            SENDING: begin
                if (count == 7) begin
                    next_state = DONE;
                end else begin
                    next_state = SENDING;
                end
            end
            DONE: begin
                next_state = IDLE;
            end
        endcase
    end
    always @(posedge clk ) begin
        if (state == SENDING) begin
            count <= count + 1;
        end else if (state == DONE||state == IDLE) begin
            count <= 0;
        end
        end
    always @(posedge clk ) begin
        if (state == START) begin
            txd <= 0;
        end else if (state == SENDING) begin
            txd <= tx_data[count];
        end else if (state == DONE|state==IDLE) begin
            txd <= 1;
        end
        end
    assign tx_busy = (state == SENDING);  
endmodule

数字系统/VS_verilog_源代码文件/homework6/tx_tb.v
//~ `New testbench
`timescale  1ns / 1ps
`include "uart_tx.v"
module tb_uart_tx;
// uart_tx Parameters
parameter PERIOD  = 10;
// uart_tx Inputs
reg   clk                                  = 0 ;
reg   [7:0]  tx_data                       = 0 ;
reg   tx_start                             = 0 ;
// uart_tx Outputs
wire  tx_busy                              ;
wire  txd                                  ;
initial
begin
    forever #(PERIOD/2)  clk=~clk;
end
uart_tx  u_uart_tx (
    .clk                     ( clk             ),
    .tx_data                 ( tx_data   [7:0] ),
    .tx_start                ( tx_start        ),

    .tx_busy                 ( tx_busy         ),
    .txd                     ( txd             )
);
initial
begin
$dumpfile("tb_uart_tx.vcd");
$dumpvars(0,tb_uart_tx);
tx_data = 8'b00100000;
tx_start = 1;
#40
tx_start = 0;
#200;
    $finish;
end

endmodule

数字系统/VS_verilog_源代码文件/homework6/tb_uart_tx.vcd
$date
	Tue May 30 16:30:38 2023
$end
$version
	Icarus Verilog
$end
$timescale
	1ps
$end
$scope module tb_uart_tx $end
$var wire 1 ! txd $end
$var wire 1 " tx_busy $end
$var reg 1 # clk $end
$var reg 8 $ tx_data [7:0] $end
$var reg 1 % tx_start $end
$scope module u_uart_tx $end
$var wire 1 # clk $end
$var wire 8 & tx_data [7:0] $end
$var wire 1 % tx_start $end
$var wire 1 " tx_busy $end
$var reg 3 ' count [2:0] $end
$var reg 3 ( next_state [2:0] $end
$var reg 3 ) state [2:0] $end
$var reg 1 ! txd $end
$upscope $end
$upscope $end
$enddefinitions $end
#0
$dumpvars
b0 )
b1 (
bx '
b100000 &
1%
b100000 $
0#
0"
x!
$end
#5000
b10 (
b1 )
b0 '
1!
1#
#10000
0#
#15000
0!
1"
b10 )
1#
#20000
0#
#25000
b1 '
1#
#30000
0#
#35000
b10 '
1#
#40000
0#
0%
#45000
b11 '
1#
#50000
0#
#55000
b100 '
1#
#60000
0#
#65000
b101 '
1#
#70000
0#
#75000
1!
b110 '
1#
#80000
0#
#85000
b11 (
b111 '
0!
1#
#90000
0#
#95000
b0 (
b0 '
0"
b11 )
1#
#100000
0#
#105000
b0 )
1!
1#
