数字系统/VS_verilog_源代码文件/lab6/fsm.v
module fsm (
     input Clock,Reset,
     input N0d0,Nd0,
     output reg Nload,Cload,Out,MuxC,MuxN
);
    parameter s0 = 0,s1 = 1,s2 = 2,s3 = 3,s4 = 4;
    reg [2:0] state;
    always @(posedge Clock or negedge Reset) begin
        if(~Reset)
            state <= s0;
        else
            case(state)
                s0: state <= s1;
                s1:begin
                  if (Nd0) begin
                    state <= s4;
                  end
                    else if (N0d0) begin
                        state <= s3;
                    end
                    else begin
                        state <= s2;
                    end
                end 
                s2: state <= s1;
                s3: state <= s2;
                s4: state <= s4;
                default : state <= s0;
            endcase
    end
    always @(state) begin
        case (state)
            s0: begin
                Nload <= 1'b1;
                Cload <= 1'b1;
                Out <= 1'b0;
                MuxC <= 1'b1;
                MuxN <= 1'b1;
            end
            s1: begin
                Nload <= 1'b0;
                Cload <= 1'b0;
                Out <= 1'b0;
                MuxC <= 1'b0;
                MuxN <= 1'b0;
            end
            s2: begin
                Nload <= 1'b1;
                Cload <= 1'b0;
                Out <= 1'b0;
                MuxC <= 1'b0;
                MuxN <= 1'b0;
            end
            s3: begin
                Nload <= 1'b0;
                Cload <= 1'b1;
                Out <= 1'b0;
                MuxC <= 1'b0;
                MuxN <= 1'b0;
            end
            s4: begin
                Nload <= 1'b0;
                Cload <= 1'b0;
                Out <= 1'b1;
                MuxC <= 1'b0;
                MuxN <= 1'b0;
            end
            default: begin
                Nload <= 1'b0;
                Cload <= 1'b0;
                Out <= 1'b0;
                MuxC <= 1'b0;
                MuxN <= 1'b0;
            end
        endcase
    end
endmodule

数字系统/VS_verilog_源代码文件/lab6/tri_buffer.v
module tri_buffer 
    #(parameter n = 4)
    (input E,
    input [n-1:0] D,
    output[n-1:0] Y
    );
    assign Y = E ? D : {n{1'bz}} ;
endmodule

数字系统/VS_verilog_源代码文件/lab6/adder.v
module adder
(
      input [3:0]a,b,            
      output [3:0]sum             
);     
		
 assign sum=a+b;
endmodule

数字系统/VS_verilog_源代码文件/lab6/shifter.v
module shifter 
 #(parameter n = 8)
(
    input [1:0]s,
    input [n-1:0]date,
    output reg [n-1:0]outdate
);
always @(s or date) begin
    case(s)
        2'b00: outdate = date;
        2'b01: outdate = date<<1;
        2'b10: outdate = date>>1;
        2'b11: outdate = {date[0],date[n-1:1]};
    endcase
end
endmodule

数字系统/VS_verilog_源代码文件/lab6/register.v
module register
#(parameter n=8)
(
 input clock,clear,load,
 input [n-1:0] D,
    output reg [n-1:0] Q
);
    always @(posedge clock or negedge clear ) begin
        if (clear==0) begin
            Q<=0;
        end
        else if (load==1) begin
            Q<=D;
        end
    end
endmodule

数字系统/VS_verilog_源代码文件/lab6/mux21.v
module mux21
#(parameter n=4)
(
    input S,  
    input [n-1:0]D1,
    input [n-1:0]D0,
    output [n-1:0]Y
);
    
    assign Y = S ? D1 : D0;
endmodule

数字系统/VS_verilog_源代码文件/lab6/dp.v
`include "adder.v"
`include "mux21.v"
`include "register.v"
`include "shifter.v"
`include "tri_buffer.v"
module dp(
    input Clock,Reset,
    input MuxN,LoadN,MuxC,LoadC,Out,
    input [7:0]N,
    output Data,
    output Nd0,N0d0
);
    wire[7:0] dp_MuxN,dp_shift,dp_N;
    wire[3:0] dp_MuxC,dp_sum,dp_C;
    wire C4;
    mux21#(8) muxN(
        .S(MuxN),
        .D1(N),
        .D0(dp_shift),
        .Y(dp_MuxN)
    );
    mux21#(4) muxC(
        .S(MuxC),
        .D1(4'b0000),
        .D0(dp_sum),
        .Y(dp_MuxC)
    );
    register#(8) regN(
        .clock(Clock),
        .clear(Reset),
        .load(LoadN),
        .D(dp_MuxN),
        .Q(dp_N)
    );
    register#(4) regC(
        .clock(Clock),
        .clear(Reset),
        .load(LoadC),
        .D(dp_MuxC),
        .Q(dp_C)
    );
    shifter#(8) shift(
        .s(2'b10),
        .date(dp_N),
        .outdate(dp_shift)
    );
    adder sum(
        .a(dp_C),
        .b(4'b0001),
        .sum(dp_sum)
    );
    assign C4=(dp_C==4'b0100)?1'b1:1'b0;
    assign Nd0=(dp_N==0)?1'b1:1'b0;
    assign N0d0=dp_N[0];
    tri_buffer#(1) buffer(
        .E(Out),
        .D(C4),
        .Y(Data)
    );
endmodule

数字系统/VS_verilog_源代码文件/lab6/top.v
`include "dp.v"
`include "fsm.v"
module top (
    input Clock,Reset,
    output Data,
    input [7:0]N
);
wire MuxN,LoadN,MuxC,LoadC,Out,Nd0,N0d0;
  dp dp(
      .Clock(Clock),
      .Reset(Reset),
      .MuxN(MuxN),
      .LoadN(LoadN),
      .MuxC(MuxC),
      .LoadC(LoadC),
      .Out(Out),
      .N(N),
      .Data(Data),
      .Nd0(Nd0),
      .N0d0(N0d0)
  );
  fsm fsm(
      .Clock(Clock),
      .Reset(Reset),
      .N0d0(N0d0),
      .Nd0(Nd0),
      .Nload(LoadN),
      .Cload(LoadC),
      .Out(Out),
      .MuxC(MuxC),
      .MuxN(MuxN)
  );
endmodule

数字系统/VS_verilog_源代码文件/lab6/tb.v
`timescale  1ns / 1ps
`include "top.v"
module tb_top;

// top Parameters
parameter PERIOD  = 10;


// top Inputs
reg   Clock                                = 0 ;
reg   Reset                                = 0 ;
reg   [7:0]  N                             = 0 ;

// top Outputs
wire  Data                                 ;


initial
begin
    forever #(PERIOD/2)  Clock=~Clock;
end



top  u_top (
    .Clock                   ( Clock        ),
    .Reset                   ( Reset        ),
    .N                       ( N      [7:0] ),

    .Data                    ( Data         )
);

initial
begin
    $dumpfile("tb_top.vcd");
    $dumpvars(0,tb_top);
    N=8'b10101100;
    Reset = 0;
    #10;
    Reset = 1;
    #10;
    
    #10000;
    $finish;
end

endmodule

数字系统/VS_verilog_源代码文件/lab6/tb_top.vcd
$date
	Sat May 20 00:10:49 2023
$end
$version
	Icarus Verilog
$end
$timescale
	1ps
$end
$scope module tb_top $end
$var wire 1 ! Data $end
$var reg 1 " Clock $end
$var reg 8 # N [7:0] $end
$var reg 1 $ Reset $end
$scope module u_top $end
$var wire 1 " Clock $end
$var wire 8 % N [7:0] $end
$var wire 1 $ Reset $end
$var wire 1 & Out $end
$var wire 1 ' Nd0 $end
$var wire 1 ( N0d0 $end
$var wire 1 ) MuxN $end
$var wire 1 * MuxC $end
$var wire 1 + LoadN $end
$var wire 1 , LoadC $end
$var wire 1 ! Data $end
$scope module dp $end
$var wire 1 " Clock $end
$var wire 8 - N [7:0] $end
$var wire 1 $ Reset $end
$var wire 4 . dp_sum [3:0] $end
$var wire 8 / dp_shift [7:0] $end
$var wire 8 0 dp_N [7:0] $end
$var wire 8 1 dp_MuxN [7:0] $end
$var wire 4 2 dp_MuxC [3:0] $end
$var wire 4 3 dp_C [3:0] $end
$var wire 1 & Out $end
$var wire 1 ' Nd0 $end
$var wire 1 ( N0d0 $end
$var wire 1 ) MuxN $end
$var wire 1 * MuxC $end
$var wire 1 + LoadN $end
$var wire 1 , LoadC $end
$var wire 1 ! Data $end
$var wire 1 4 C4 $end
$scope module buffer $end
$var wire 1 4 D $end
$var wire 1 ! Y $end
$var wire 1 & E $end
$upscope $end
$scope module muxC $end
$var wire 4 5 D1 [3:0] $end
$var wire 4 6 Y [3:0] $end
$var wire 1 * S $end
$var wire 4 7 D0 [3:0] $end
$upscope $end
$scope module muxN $end
$var wire 8 8 D1 [7:0] $end
$var wire 8 9 Y [7:0] $end
$var wire 1 ) S $end
$var wire 8 : D0 [7:0] $end
$upscope $end
$scope module regC $end
$var wire 4 ; D [3:0] $end
$var wire 1 $ clear $end
$var wire 1 " clock $end
$var wire 1 , load $end
$var reg 4 < Q [3:0] $end
$upscope $end
$scope module regN $end
$var wire 8 = D [7:0] $end
$var wire 1 $ clear $end
$var wire 1 " clock $end
$var wire 1 + load $end
$var reg 8 > Q [7:0] $end
$upscope $end
$scope module shift $end
$var wire 8 ? date [7:0] $end
$var wire 2 @ s [1:0] $end
$var reg 8 A outdate [7:0] $end
$upscope $end
$scope module sum $end
$var wire 4 B a [3:0] $end
$var wire 4 C b [3:0] $end
$var wire 4 D sum [3:0] $end
$upscope $end
$upscope $end
$scope module fsm $end
$var wire 1 " Clock $end
$var wire 1 ( N0d0 $end
$var wire 1 ' Nd0 $end
$var wire 1 $ Reset $end
$var reg 1 , Cload $end
$var reg 1 * MuxC $end
$var reg 1 ) MuxN $end
$var reg 1 + Nload $end
$var reg 1 & Out $end
$var reg 3 E state [2:0] $end
$upscope $end
$upscope $end
$upscope $end
$enddefinitions $end
#0
$dumpvars
b0 E
b1 D
b1 C
b0 B
b0 A
b10 @
b0 ?
b0 >
b10101100 =
b0 <
b0 ;
b0 :
b10101100 9
b10101100 8
b1 7
b0 6
b0 5
04
b0 3
b0 2
b10101100 1
b0 0
b0 /
b1 .
b10101100 -
1,
1+
1*
1)
0(
1'
0&
b10101100 %
0$
b10101100 #
0"
z!
$end
#5000
1"
#10000
0"
1$
#15000
b1010110 1
b1010110 9
b1010110 =
b1 2
b1 6
b1 ;
0)
0*
0,
0+
b1010110 /
b1010110 :
b1010110 A
0'
b10101100 0
b10101100 >
b10101100 ?
b1 E
1"
#20000
0"
#25000
1+
b10 E
1"
#30000
0"
#35000
0+
b101011 1
b101011 9
b101011 =
b101011 /
b101011 :
b101011 A
b1010110 0
b1010110 >
b1010110 ?
b1 E
1"
#40000
0"
#45000
1+
b10 E
1"
#50000
0"
#55000
0+
b10101 1
b10101 9
b10101 =
b10101 /
b10101 :
b10101 A
1(
b101011 0
b101011 >
b101011 ?
b1 E
1"
#60000
0"
#65000
1,
b11 E
1"
#70000
0"
#75000
0,
1+
b10 2
b10 6
b10 ;
b10 .
b10 7
b10 D
b1 3
b1 <
b1 B
b10 E
1"
#80000
0"
#85000
0+
b1010 1
b1010 9
b1010 =
b1010 /
b1010 :
b1010 A
b1 E
b10101 0
b10101 >
b10101 ?
1"
#90000
0"
#95000
1,
b11 E
1"
#100000
0"
#105000
0,
1+
b11 2
b11 6
b11 ;
b10 E
b11 .
b11 7
b11 D
b10 3
b10 <
b10 B
1"
#110000
0"
#115000
0+
b101 1
b101 9
b101 =
b101 /
b101 :
b101 A
0(
b1010 0
b1010 >
b1010 ?
b1 E
1"
#120000
0"
#125000
1+
b10 E
1"
#130000
0"
#135000
0+
b10 1
b10 9
b10 =
b10 /
b10 :
b10 A
1(
b101 0
b101 >
b101 ?
b1 E
1"
#140000
0"
#145000
1,
b11 E
1"
#150000
0"
#155000
0,
1+
b100 2
b100 6
b100 ;
b100 .
b100 7
b100 D
b11 3
b11 <
b11 B
b10 E
1"
#160000
0"
#165000
0+
b1 1
b1 9
b1 =
b1 /
b1 :
b1 A
0(
b1 E
b10 0
b10 >
b10 ?
1"
#170000
0"
#175000
1+
b10 E
1"
#180000
0"
#185000
0+
b0 1
b0 9
b0 =
b0 /
b0 :
b0 A
1(
b1 E
b1 0
b1 >
b1 ?
1"
#190000
0"
#195000
1,
b11 E
1"
#200000
0"
#205000
0,
1+
b101 2
b101 6
b101 ;
14
b10 E
b101 .
b101 7
b101 D
b100 3
b100 <
b100 B
1"
#210000
0"
#215000
0+
0(
1'
b0 0
b0 >
b0 ?
b1 E
1"
#220000
0"
#225000
1!
1&
b100 E
1"
