数字系统/VS_verilog_源代码文件/lab7/cu.v
module cu (
    input clk,
    input rst,
    input [2:0] IR75,
    input Anot0,
    output reg IRload,
    output reg PCload,
    output reg JNZmux,
    output reg Halt_out,
    output reg OutE,
    output reg Aload,
    output reg INmux
);
    parameter Fetch = 3'b000,Decode = 3'b001,Input = 3'b011,Output = 3'b100,Dec=3'b101,JNZ=3'b110,Halt=3'b111;
    reg[2:0] state,next_state;
    always @(posedge clk or negedge rst  ) begin
        if(!rst) begin
            state <= Fetch;
        end
        else begin
            state <= next_state;
        end        
    end
    always @(posedge clk or negedge rst) begin
        if (!rst) begin
            IRload<=1;
            PCload<=1;
            JNZmux<=0;
            Halt_out<=0;
            OutE<=0;
            Aload<=0;
            INmux<=0;
        end
        else begin case (next_state)
            Fetch: begin
                IRload<=1;
                PCload<=1;
                JNZmux<=0;
                Halt_out<=0;
                OutE<=0;
                Aload<=0;
                INmux<=0;
            end
            Decode: begin
                IRload<=0;
                PCload<=0;
                JNZmux<=0;
                Halt_out<=0;
                OutE<=0;
                Aload<=0;
                INmux<=0;
            end
            Input: begin
                IRload<=0;
                PCload<=0;
                JNZmux<=0;
                Halt_out<=0;
                OutE<=0;
                Aload<=1;
                INmux<=1;
            end
            Output: begin
                IRload<=0;
                PCload<=0;
                JNZmux<=0;
                Halt_out<=0;
                OutE<=1;
                Aload<=0;
                INmux<=0;
            end
            Dec: begin
                IRload<=0;
                PCload<=0;
                JNZmux<=0;
                Halt_out<=0;
                OutE<=0;
                Aload<=1;
                INmux<=0;
            end
            JNZ: begin
                IRload<=0;
                PCload<=(Anot0==1)?1:0;
                JNZmux<=1;
                Halt_out<=0;
                OutE<=0;
                Aload<=0;
                INmux<=0;
            end
            Halt: begin
                IRload<=0;
                PCload<=0;
                JNZmux<=0;
                Halt_out<=1;
                OutE<=0;
                Aload<=0;
                INmux<=0;
            end
            default: begin
                IRload<=0;
                PCload<=0;
                JNZmux<=0;
                Halt_out<=0;
                OutE<=0;
                Aload<=0;
                INmux<=0;
            end
        endcase
        end
    end

    always @(state or IR75 ) begin
        case (state)
        Fetch: begin
            next_state=Decode;
        end
        Decode: begin
            if (IR75==3'b011) next_state=Input;
            else if (IR75==3'b100) next_state=Output;
            else if (IR75==3'b101) next_state=Dec;
            else if (IR75==3'b110) next_state=JNZ;
            else if (IR75==3'b111) next_state=Halt;
            else next_state=Fetch;
        end
        Input: begin
           next_state=Fetch;
        end
        Output: begin
            next_state=Fetch;
        end
        Dec: begin
            next_state=Fetch;
        end
        JNZ: begin
            next_state=Fetch;
        end
        Halt: begin
            next_state=Halt;
        end
        default: begin
            next_state=Fetch;
        end
        endcase
    end
endmodule

数字系统/VS_verilog_源代码文件/lab6/tri_buffer.v
module tri_buffer 
    #(parameter n = 4)
    (input E,
    input [n-1:0] D,
    output[n-1:0] Y
    );
    assign Y = E ? D : {n{1'bz}} ;
endmodule

数字系统/VS_verilog_源代码文件/lab7/rom_16x8.v
module rom 
#(parameter size = 4)
    (
    input E,
    input [size-1:0] addr,
    output [7:0] data
    );
reg [7:0] mem[0:size**2-1];
    initial begin
        mem[0] <= 8'b01100000;
        mem[1] <= 8'b10000000;
        mem[2] <= 8'b10100000;
        mem[3] <= 8'b11000001;
        mem[4] <= 8'b11111111;
    end
    assign  data = E? mem[addr] : 8'bzzzzzzzz;
endmodule

数字系统/lab/lab7/decrement.v
module decrement (
    input [7:0] A,
    output [7:0] F
);
    assign F = A - 1;
endmodule

数字系统/lab/lab7/increment.v
module increment (
    input [3:0] A,
    output [3:0] F
);
    assign F = A + 1;
    
endmodule

数字系统/lab/lab7/mux21.v
module mux21
#(parameter n=4)
(
    input S,  
    input [n-1:0]A,
    input [n-1:0]B,
    output [n-1:0]Y
);
    
    assign Y = S ? A : B;
endmodule

数字系统/lab/lab7/Register.v
module Register
#(parameter n=8)
(
 input clk,rst,load,
 input [n-1:0] D,
    output reg [n-1:0] Q
);
    always @(posedge clk or negedge rst ) begin
        if (rst==0) begin
            Q<=0;
        end
        else if (load==1) begin
            Q<=D;
        end
    end
endmodule

数字系统/lab/lab7/dp.v
`include "decrement.v"
`include "increment.v"
`include "mux21.v"
`include "Register.v"
`include "rom_16x8.v"
`include "tri_buffer.v"
module dp (
    input clk,rst,
    input IRload,PCload,
    input JNZmux,INmux,
    input Aload,
    input OutE,
    input [7:0] Input,
    output [2:0]IR75,
    output Anot0,
    output [7:0] Output
);
    wire[7:0] dp_ROMQ,dp_IR;
    wire[3:0] dp_increment,dp_PC,dp_JNZmux;
    wire[7:0] dp_INmux,dp_A,dp_decrement;
    Register #(8) regIR (.clk(clk),.rst(rst),.load(IRload),.D(dp_ROMQ),.Q(dp_IR));
    Register #(4) regPC (.clk(clk),.rst(rst),.load(PCload),.D(dp_JNZmux),.Q(dp_PC));
    Register #(8) regA (.clk(clk),.rst(rst),.load(Aload),.D(dp_INmux),.Q(dp_A));
    mux21 #(8) muxIN (.A(Input),.B(dp_decrement),.S(INmux),.Y(dp_INmux));
    mux21 #(4) muxJNZ (.A(dp_IR[3:0]),.B(dp_increment),.S(JNZmux),.Y(dp_JNZmux));
    increment inc (.A(dp_PC),.F(dp_increment));
    decrement dec (.A(dp_A),.F(dp_decrement));
    rom rom (.E(1'b1),.addr(dp_PC),.data(dp_ROMQ));
    tri_buffer #(8) buffer (.E(OutE),.D(dp_A),.Y(Output));
    assign IR75 = dp_IR[7:5];
    assign Anot0 = (dp_A!=0)? 1'b1 : 1'b0;

endmodule

数字系统/lab/lab7/top.v
`include "dp.v"
`include "cu.v"
module top (
    input clk,rst,
    input [7:0] A,
    output [7:0] Output,
    output Halt_out
);
    wire IRload,PCload,JNZmux,OutE,Aload,INmux;
    wire [2:0] IR75;
    wire Anot0;
    dp dp (
        .clk(clk),
        .rst(rst),
        .IRload(IRload),
        .PCload(PCload),
        .JNZmux(JNZmux),
        .OutE(OutE),
        .Aload(Aload),
        .INmux(INmux),
        .Input(A),
        .IR75(IR75),
        .Anot0(Anot0),
        .Output(Output));
    cu cu (
        .clk(clk),
        .rst(rst),
        .IR75(IR75),
        .Anot0(Anot0),
        .IRload(IRload),
        .PCload(PCload),
        .JNZmux(JNZmux),
        .Halt_out(Halt_out),
        .OutE(OutE),
        .Aload(Aload),
        .INmux(INmux));
endmodule

数字系统/lab/lab7/tb.v
//~ `New testbench
`timescale  1ns / 1ps
`include "top.v"

module tb_top;

// top Parameters
parameter PERIOD  = 10;


// top Inputs
reg   clk                                  = 0 ;
reg   rst                                  = 0 ;
reg   [7:0]  A                             = 0 ;

// top Outputs
wire  [7:0]  Output                        ;
wire  Halt_out                             ;


initial
begin
    forever #(PERIOD/2)  clk=~clk;
end



top  u_top (
    .clk                     ( clk             ),
    .rst                     ( rst             ),
    .A                       ( A         [7:0] ),

    .Output                  ( Output    [7:0] ),
    .Halt_out                ( Halt_out        )
);

initial
begin
$dumpfile("tb_top.vcd");
$dumpvars(0,tb_top);
A=8'h42;
rst=1;
#1
rst=0;
#1
rst=1;
#10000
    $finish;
end

endmodule

数字系统/VS_verilog_源代码文件/lab7/tb_top.vcd
$date
	Sun May 28 17:05:03 2023
$end
$version
	Icarus Verilog
$end
$timescale
	1ps
$end
$scope module tb_top $end
$var wire 8 ! Output [7:0] $end
$var wire 1 " Halt_out $end
$var reg 8 # A [7:0] $end
$var reg 1 $ clk $end
$var reg 1 % rst $end
$scope module u_top $end
$var wire 8 & A [7:0] $end
$var wire 1 $ clk $end
$var wire 1 % rst $end
$var wire 1 ' PCload $end
$var wire 8 ( Output [7:0] $end
$var wire 1 ) OutE $end
$var wire 1 * JNZmux $end
$var wire 1 + IRload $end
$var wire 3 , IR75 [2:0] $end
$var wire 1 - INmux $end
$var wire 1 " Halt_out $end
$var wire 1 . Anot0 $end
$var wire 1 / Aload $end
$scope module cu $end
$var wire 1 $ clk $end
$var wire 1 % rst $end
$var wire 3 0 IR75 [2:0] $end
$var wire 1 . Anot0 $end
$var reg 1 / Aload $end
$var reg 1 " Halt_out $end
$var reg 1 - INmux $end
$var reg 1 + IRload $end
$var reg 1 * JNZmux $end
$var reg 1 ) OutE $end
$var reg 1 ' PCload $end
$var reg 3 1 next_state [2:0] $end
$var reg 3 2 state [2:0] $end
$upscope $end
$scope module dp $end
$var wire 1 / Aload $end
$var wire 1 - INmux $end
$var wire 1 + IRload $end
$var wire 8 3 Input [7:0] $end
$var wire 1 * JNZmux $end
$var wire 1 ) OutE $end
$var wire 1 ' PCload $end
$var wire 1 $ clk $end
$var wire 1 % rst $end
$var wire 4 4 dp_increment [3:0] $end
$var wire 8 5 dp_decrement [7:0] $end
$var wire 8 6 dp_ROMQ [7:0] $end
$var wire 4 7 dp_PC [3:0] $end
$var wire 4 8 dp_JNZmux [3:0] $end
$var wire 8 9 dp_IR [7:0] $end
$var wire 8 : dp_INmux [7:0] $end
$var wire 8 ; dp_A [7:0] $end
$var wire 8 < Output [7:0] $end
$var wire 3 = IR75 [2:0] $end
$var wire 1 . Anot0 $end
$scope module buffer $end
$var wire 1 ) E $end
$var wire 8 > Y [7:0] $end
$var wire 8 ? D [7:0] $end
$upscope $end
$scope module dec $end
$var wire 8 @ F [7:0] $end
$var wire 8 A A [7:0] $end
$upscope $end
$scope module inc $end
$var wire 4 B F [3:0] $end
$var wire 4 C A [3:0] $end
$upscope $end
$scope module muxIN $end
$var wire 8 D A [7:0] $end
$var wire 8 E B [7:0] $end
$var wire 1 - S $end
$var wire 8 F Y [7:0] $end
$upscope $end
$scope module muxJNZ $end
$var wire 4 G A [3:0] $end
$var wire 4 H B [3:0] $end
$var wire 1 * S $end
$var wire 4 I Y [3:0] $end
$upscope $end
$scope module regA $end
$var wire 8 J D [7:0] $end
$var wire 1 $ clk $end
$var wire 1 / load $end
$var wire 1 % rst $end
$var reg 8 K Q [7:0] $end
$upscope $end
$scope module regIR $end
$var wire 1 $ clk $end
$var wire 1 + load $end
$var wire 1 % rst $end
$var wire 8 L D [7:0] $end
$var reg 8 M Q [7:0] $end
$upscope $end
$scope module regPC $end
$var wire 4 N D [3:0] $end
$var wire 1 $ clk $end
$var wire 1 ' load $end
$var wire 1 % rst $end
$var reg 4 O Q [3:0] $end
$upscope $end
$scope module rom $end
$var wire 1 P E $end
$var wire 4 Q addr [3:0] $end
$var wire 8 R data [7:0] $end
$upscope $end
$upscope $end
$upscope $end
$upscope $end
$enddefinitions $end
#0
$dumpvars
bx R
bx Q
1P
bx O
bx N
bx M
bx L
bx K
bx J
bx I
bx H
bx G
bx F
bx E
b1000010 D
bx C
bx B
bx A
bx @
bx ?
bz >
bx =
bz <
bx ;
bx :
bx 9
bx 8
bx 7
bx 6
bx 5
bx 4
b1000010 3
bx 2
bx 1
bx 0
0/
x.
0-
bx ,
0+
0*
0)
bz (
0'
b1000010 &
1%
0$
b1000010 #
0"
bz !
$end
#1000
b1 1
b11111111 :
b11111111 F
b11111111 J
0.
b1 8
b1 I
b1 N
b0 ,
b0 0
b0 =
b0 G
1'
1+
b0 2
b11111111 5
b11111111 @
b11111111 E
b0 ;
b0 ?
b0 A
b0 K
b1100000 6
b1100000 L
b1100000 R
b1 4
b1 B
b1 H
b0 7
b0 C
b0 O
b0 Q
b0 9
b0 M
0%
#2000
1%
#5000
b11 ,
b11 0
b11 =
b10 8
b10 I
b10 N
b11 1
b1100000 9
b1100000 M
b10000000 6
b10000000 L
b10000000 R
b10 4
b10 B
b10 H
b1 7
b1 C
b1 O
b1 Q
b1 2
0'
0+
1$
#10000
0$
#15000
b1000010 :
b1000010 F
b1000010 J
b0 1
1-
1/
b11 2
1$
#20000
0$
#25000
1.
b1 1
b1000001 :
b1000001 F
b1000001 J
b1000001 5
b1000001 @
b1000001 E
b1000010 ;
b1000010 ?
b1000010 A
b1000010 K
b0 2
0-
0/
1'
1+
1$
#30000
0$
#35000
b100 1
b11 8
b11 I
b11 N
b100 ,
b100 0
b100 =
0'
0+
b1 2
b10100000 6
b10100000 L
b10100000 R
b11 4
b11 B
b11 H
b10 7
b10 C
b10 O
b10 Q
b10000000 9
b10000000 M
1$
#40000
0$
#45000
b0 1
b1000010 !
b1000010 (
b1000010 <
b1000010 >
b100 2
1)
1$
#50000
0$
#55000
bz !
bz (
bz <
bz >
b1 1
0)
1'
1+
b0 2
1$
#60000
0$
#65000
b101 ,
b101 0
b101 =
b100 8
b100 I
b100 N
b101 1
b10100000 9
b10100000 M
b11000001 6
b11000001 L
b11000001 R
b100 4
b100 B
b100 H
b11 7
b11 C
b11 O
b11 Q
b1 2
0'
0+
1$
#70000
0$
#75000
b0 1
1/
b101 2
1$
#80000
0$
#85000
b1000000 :
b1000000 F
b1000000 J
b1 1
b1000000 5
b1000000 @
b1000000 E
b1000001 ;
b1000001 ?
b1000001 A
b1000001 K
b0 2
0/
1'
1+
1$
#90000
0$
#95000
b110 1
b101 8
b101 I
b101 N
b110 ,
b110 0
b110 =
b1 G
0'
0+
b1 2
b11111111 6
b11111111 L
b11111111 R
b101 4
b101 B
b101 H
b100 7
b100 C
b100 O
b100 Q
b11000001 9
b11000001 M
1$
#100000
0$
#105000
b0 1
b1 8
b1 I
b1 N
b110 2
1*
1'
1$
#110000
0$
#115000
b10 8
b10 I
b10 N
b1 1
0*
1+
b0 2
b10000000 6
b10000000 L
b10000000 R
b10 4
b10 B
b10 H
b1 7
b1 C
b1 O
b1 Q
1$
#120000
0$
#125000
b100 ,
b100 0
b100 =
b0 G
b11 8
b11 I
b11 N
b100 1
b10000000 9
b10000000 M
b10100000 6
b10100000 L
b10100000 R
b11 4
b11 B
b11 H
b10 7
b10 C
b10 O
b10 Q
b1 2
0'
0+
1$
#130000
0$
#135000
b1000001 !
b1000001 (
b1000001 <
b1000001 >
b0 1
1)
b100 2
1$
#140000
0$
#145000
b1 1
bz !
bz (
bz <
bz >
b0 2
0)
1'
1+
1$
#150000
0$
#155000
b101 1
b100 8
b100 I
b100 N
b101 ,
b101 0
b101 =
0'
0+
b1 2
b11000001 6
b11000001 L
b11000001 R
b100 4
b100 B
b100 H
b11 7
b11 C
b11 O
b11 Q
b10100000 9
b10100000 M
1$
#160000
0$
#165000
b0 1
b101 2
1/
1$
#170000
0$
#175000
b1 1
b111111 :
b111111 F
b111111 J
0/
1'
1+
b0 2
b111111 5
b111111 @
b111111 E
b1000000 ;
b1000000 ?
b1000000 A
b1000000 K
1$
#180000
0$
#185000
b110 ,
b110 0
b110 =
b1 G
b101 8
b101 I
b101 N
b110 1
b11000001 9
b11000001 M
b11111111 6
b11111111 L
b11111111 R
b101 4
b101 B
b101 H
b100 7
b100 C
b100 O
b100 Q
b1 2
0'
0+
1$
#190000
0$
#195000
b1 8
b1 I
b1 N
b0 1
1*
1'
b110 2
1$
#200000
0$
#205000
b1 1
b10 8
b10 I
b10 N
b10000000 6
b10000000 L
b10000000 R
b10 4
b10 B
b10 H
b1 7
b1 C
b1 O
b1 Q
b0 2
0*
1+
1$
#210000
0$
#215000
b100 1
b11 8
b11 I
b11 N
b100 ,
b100 0
b100 =
b0 G
0'
0+
b1 2
b10100000 6
b10100000 L
b10100000 R
b11 4
b11 B
b11 H
b10 7
b10 C
b10 O
b10 Q
b10000000 9
b10000000 M
1$
#220000
0$
#225000
b0 1
b1000000 !
b1000000 (
b1000000 <
b1000000 >
b100 2
1)
1$
#230000
0$
#235000
bz !
bz (
bz <
bz >
b1 1
0)
1'
1+
b0 2
1$
#240000
0$
#245000
b101 ,
b101 0
b101 =
b100 8
b100 I
b100 N
b101 1
b10100000 9
b10100000 M
b11000001 6
b11000001 L
b11000001 R
b100 4
b100 B
b100 H
b11 7
b11 C
b11 O
b11 Q
b1 2
0'
0+
1$
#250000
0$
#255000
b0 1
1/
b101 2
1$
#260000
0$
#265000
b111110 :
b111110 F
b111110 J
b1 1
b111110 5
b111110 @
b111110 E
b111111 ;
b111111 ?
b111111 A
b111111 K
b0 2
0/
1'
1+
1$
#270000
0$
#275000
b110 1
b101 8
b101 I
b101 N
b110 ,
b110 0
b110 =
b1 G
0'
0+
b1 2
b11111111 6
b11111111 L
b11111111 R
b101 4
b101 B
b101 H
b100 7
b100 C
b100 O
b100 Q
b11000001 9
b11000001 M
1$
#280000
0$
#285000
b0 1
b1 8
b1 I
b1 N
b110 2
1*
1'
1$
#290000
0$
#295000
b10 8
b10 I
b10 N
b1 1
0*
1+
b0 2
b10000000 6
b10000000 L
b10000000 R
b10 4
b10 B
b10 H
b1 7
b1 C
b1 O
b1 Q
1$
#300000
0$
#305000
b100 ,
b100 0
b100 =
b0 G
b11 8
b11 I
b11 N
b100 1
b10000000 9
b10000000 M
b10100000 6
b10100000 L
b10100000 R
b11 4
b11 B
b11 H
b10 7
b10 C
b10 O
b10 Q
b1 2
0'
0+
1$
#310000
0$
#315000
b111111 !
b111111 (
b111111 <
b111111 >
b0 1
1)
b100 2
1$
#320000
0$
#325000
b1 1
bz !
bz (
bz <
bz >
b0 2
0)
1'
1+
1$
#330000
0$
#335000
b101 1
b100 8
b100 I
b100 N
b101 ,
b101 0
b101 =
0'
0+
b1 2
b11000001 6
b11000001 L
b11000001 R
b100 4
b100 B
b100 H
b11 7
b11 C
b11 O
b11 Q
b10100000 9
b10100000 M
1$
#340000
0$
#345000
b0 1
b101 2
1/
1$
#350000
0$
#355000
b1 1
b111101 :
b111101 F
b111101 J
0/
1'
1+
b0 2
b111101 5
b111101 @
b111101 E
b111110 ;
b111110 ?
b111110 A
b111110 K
1$
#360000
0$
#365000
b110 ,
b110 0
b110 =
b1 G
b101 8
b101 I
b101 N
b110 1
b11000001 9
b11000001 M
b11111111 6
b11111111 L
b11111111 R
b101 4
b101 B
b101 H
b100 7
b100 C
b100 O
b100 Q
b1 2
0'
0+
1$
#370000
0$
#375000
b1 8
b1 I
b1 N
b0 1
1*
1'
b110 2
1$
#380000
0$
#385000
b1 1
b10 8
b10 I
b10 N
b10000000 6
b10000000 L
b10000000 R
b10 4
b10 B
b10 H
b1 7
b1 C
b1 O
b1 Q
b0 2
0*
1+
1$
#390000
0$
#395000
b100 1
b11 8
b11 I
b11 N
b100 ,
b100 0
b100 =
b0 G
0'
0+
b1 2
b10100000 6
b10100000 L
b10100000 R
b11 4
b11 B
b11 H
b10 7
b10 C
b10 O
b10 Q
b10000000 9
b10000000 M
1$
#400000
0$
#405000
b0 1
b111110 !
b111110 (
b111110 <
b111110 >
b100 2
1)
1$
#410000
0$
#415000
bz !
bz (
bz <
bz >
b1 1
0)
1'
1+
b0 2
1$
#420000
0$
#425000
b101 ,
b101 0
b101 =
b100 8
b100 I
b100 N
b101 1
b10100000 9
b10100000 M
b11000001 6
b11000001 L
b11000001 R
b100 4
b100 B
b100 H
b11 7
b11 C
b11 O
b11 Q
b1 2
0'
0+
1$
#430000
0$
#435000
b0 1
1/
b101 2
1$
#440000
0$
#445000
b111100 :
b111100 F
b111100 J
b1 1
b111100 5
b111100 @
b111100 E
b111101 ;
b111101 ?
b111101 A
b111101 K
b0 2
0/
1'
1+
1$
#450000
0$
#455000
b110 1
b101 8
b101 I
b101 N
b110 ,
b110 0
b110 =
b1 G
0'
0+
b1 2
b11111111 6
b11111111 L
b11111111 R
b101 4
b101 B
b101 H
b100 7
b100 C
b100 O
b100 Q
b11000001 9
b11000001 M
1$
#460000
0$
#465000
b0 1
b1 8
b1 I
b1 N
b110 2
1*
1'
1$
#470000
0$
#475000
b10 8
b10 I
b10 N
b1 1
0*
1+
b0 2
b10000000 6
b10000000 L
b10000000 R
b10 4
b10 B
b10 H
b1 7
b1 C
b1 O
b1 Q
1$
#480000
0$
#485000
b100 ,
b100 0
b100 =
b0 G
b11 8
b11 I
b11 N
b100 1
b10000000 9
b10000000 M
b10100000 6
b10100000 L
b10100000 R
b11 4
b11 B
b11 H
b10 7
b10 C
b10 O
b10 Q
b1 2
0'
0+
1$
#490000
0$
#495000
b111101 !
b111101 (
b111101 <
b111101 >
b0 1
1)
b100 2
1$
#500000
0$
#505000
b1 1
bz !
bz (
bz <
bz >
b0 2
0)
1'
1+
1$
#510000
0$
#515000
b101 1
b100 8
b100 I
b100 N
b101 ,
b101 0
b101 =
0'
0+
b1 2
b11000001 6
b11000001 L
b11000001 R
b100 4
b100 B
b100 H
b11 7
b11 C
b11 O
b11 Q
b10100000 9
b10100000 M
1$
#520000
0$
#525000
b0 1
b101 2
1/
1$
#530000
0$
#535000
b1 1
b111011 :
b111011 F
b111011 J
0/
1'
1+
b0 2
b111011 5
b111011 @
b111011 E
b111100 ;
b111100 ?
b111100 A
b111100 K
1$
#540000
0$
#545000
b110 ,
b110 0
b110 =
b1 G
b101 8
b101 I
b101 N
b110 1
b11000001 9
b11000001 M
b11111111 6
b11111111 L
b11111111 R
b101 4
b101 B
b101 H
b100 7
b100 C
b100 O
b100 Q
b1 2
0'
0+
1$
#550000
0$
#555000
b1 8
b1 I
b1 N
b0 1
1*
1'
b110 2
1$
#560000
0$
#565000
b1 1
b10 8
b10 I
b10 N
b10000000 6
b10000000 L
b10000000 R
b10 4
b10 B
b10 H
b1 7
b1 C
b1 O
b1 Q
b0 2
0*
1+
1$
#570000
0$
#575000
b100 1
b11 8
b11 I
b11 N
b100 ,
b100 0
b100 =
b0 G
0'
0+
b1 2
b10100000 6
b10100000 L
b10100000 R
b11 4
b11 B
b11 H
b10 7
b10 C
b10 O
b10 Q
b10000000 9
b10000000 M
1$
#580000
0$
#585000
b0 1
b111100 !
b111100 (
b111100 <
b111100 >
b100 2
1)
1$
#590000
0$
#595000
bz !
bz (
bz <
bz >
b1 1
0)
1'
1+
b0 2
1$
#600000
0$
#605000
b101 ,
b101 0
b101 =
b100 8
b100 I
b100 N
b101 1
b10100000 9
b10100000 M
b11000001 6
b11000001 L
b11000001 R
b100 4
b100 B
b100 H
b11 7
b11 C
b11 O
b11 Q
b1 2
0'
0+
1$
#610000
0$
#615000
b0 1
1/
b101 2
1$
#620000
0$
#625000
b111010 :
b111010 F
b111010 J
b1 1
b111010 5
b111010 @
b111010 E
b111011 ;
b111011 ?
b111011 A
b111011 K
b0 2
0/
1'
1+
1$
#630000
0$
#635000
b110 1
b101 8
b101 I
b101 N
b110 ,
b110 0
b110 =
b1 G
0'
0+
b1 2
b11111111 6
b11111111 L
b11111111 R
b101 4
b101 B
b101 H
b100 7
b100 C
b100 O
b100 Q
b11000001 9
b11000001 M
1$
#640000
0$
#645000
b0 1
b1 8
b1 I
b1 N
b110 2
1*
1'
1$
#650000
0$
#655000
b10 8
b10 I
b10 N
b1 1
0*
1+
b0 2
b10000000 6
b10000000 L
b10000000 R
b10 4
b10 B
b10 H
b1 7
b1 C
b1 O
b1 Q
1$
#660000
0$
#665000
b100 ,
b100 0
b100 =
b0 G
b11 8
b11 I
b11 N
b100 1
b10000000 9
b10000000 M
b10100000 6
b10100000 L
b10100000 R
b11 4
b11 B
b11 H
b10 7
b10 C
b10 O
b10 Q
b1 2
0'
0+
1$
#670000
0$
#675000
b111011 !
b111011 (
b111011 <
b111011 >
b0 1
1)
b100 2
1$
#680000
0$
#685000
b1 1
bz !
bz (
bz <
bz >
b0 2
0)
1'
1+
1$
#690000
0$
#695000
b101 1
b100 8
b100 I
b100 N
b101 ,
b101 0
b101 =
0'
0+
b1 2
b11000001 6
b11000001 L
b11000001 R
b100 4
b100 B
b100 H
b11 7
b11 C
b11 O
b11 Q
b10100000 9
b10100000 M
1$
#700000
0$
#705000
b0 1
b101 2
1/
1$
#710000
0$
#715000
b1 1
b111001 :
b111001 F
b111001 J
0/
1'
1+
b0 2
b111001 5
b111001 @
b111001 E
b111010 ;
b111010 ?
b111010 A
b111010 K
1$
#720000
0$
#725000
b110 ,
b110 0
b110 =
b1 G
b101 8
b101 I
b101 N
b110 1
b11000001 9
b11000001 M
b11111111 6
b11111111 L
b11111111 R
b101 4
b101 B
b101 H
b100 7
b100 C
b100 O
b100 Q
b1 2
0'
0+
1$
#730000
0$
#735000
b1 8
b1 I
b1 N
b0 1
1*
1'
b110 2
1$
#740000
0$
#745000
b1 1
b10 8
b10 I
b10 N
b10000000 6
b10000000 L
b10000000 R
b10 4
b10 B
b10 H
b1 7
b1 C
b1 O
b1 Q
b0 2
0*
1+
1$
#750000
0$
#755000
b100 1
b11 8
b11 I
b11 N
b100 ,
b100 0
b100 =
b0 G
0'
0+
b1 2
b10100000 6
b10100000 L
b10100000 R
b11 4
b11 B
b11 H
b10 7
b10 C
b10 O
b10 Q
b10000000 9
b10000000 M
1$
#760000
0$
#765000
b0 1
b111010 !
b111010 (
b111010 <
b111010 >
b100 2
1)
1$
#770000
0$
#775000
bz !
bz (
bz <
bz >
b1 1
0)
1'
1+
b0 2
1$
#780000
0$
#785000
b101 ,
b101 0
b101 =
b100 8
b100 I
b100 N
b101 1
b10100000 9
b10100000 M
b11000001 6
b11000001 L
b11000001 R
b100 4
b100 B
b100 H
b11 7
b11 C
b11 O
b11 Q
b1 2
0'
0+
1$
#790000
0$
#795000
b0 1
1/
b101 2
1$
#800000
0$
#805000
b111000 :
b111000 F
b111000 J
b1 1
b111000 5
b111000 @
b111000 E
b111001 ;
b111001 ?
b111001 A
b111001 K
b0 2
0/
1'
1+
1$
#810000
0$
#815000
b110 1
b101 8
b101 I
b101 N
b110 ,
b110 0
b110 =
b1 G
0'
0+
b1 2
b11111111 6
b11111111 L
b11111111 R
b101 4
b101 B
b101 H
b100 7
b100 C
b100 O
b100 Q
b11000001 9
b11000001 M
1$
#820000
0$
#825000
b0 1
b1 8
b1 I
b1 N
b110 2
1*
1'
1$
#830000
0$
#835000
b10 8
b10 I
b10 N
b1 1
0*
1+
b0 2
b10000000 6
b10000000 L
b10000000 R
b10 4
b10 B
b10 H
b1 7
b1 C
b1 O
b1 Q
1$
#840000
0$
#845000
b100 ,
b100 0
b100 =
b0 G
b11 8
b11 I
b11 N
b100 1
b10000000 9
b10000000 M
b10100000 6
b10100000 L
b10100000 R
b11 4
b11 B
b11 H
b10 7
b10 C
b10 O
b10 Q
b1 2
0'
0+
1$
#850000
0$
#855000
b111001 !
b111001 (
b111001 <
b111001 >
b0 1
1)
b100 2
1$
#860000
0$
#865000
b1 1
bz !
bz (
bz <
bz >
b0 2
0)
1'
1+
1$
#870000
0$
#875000
b101 1
b100 8
b100 I
b100 N
b101 ,
b101 0
b101 =
0'
0+
b1 2
b11000001 6
b11000001 L
b11000001 R
b100 4
b100 B
b100 H
b11 7
b11 C
b11 O
b11 Q
b10100000 9
b10100000 M
1$
#880000
0$
#885000
b0 1
b101 2
1/
1$
#890000
0$
#895000
b1 1
b110111 :
b110111 F
b110111 J
0/
1'
1+
b0 2
b110111 5
b110111 @
b110111 E
b111000 ;
b111000 ?
b111000 A
b111000 K
1$
#900000
0$
#905000
b110 ,
b110 0
b110 =
b1 G
b101 8
b101 I
b101 N
b110 1
b11000001 9
b11000001 M
b11111111 6
b11111111 L
b11111111 R
b101 4
b101 B
b101 H
b100 7
b100 C
b100 O
b100 Q
b1 2
0'
0+
1$
#910000
0$
#915000
b1 8
b1 I
b1 N
b0 1
1*
1'
b110 2
1$
#920000
0$
#925000
b1 1
b10 8
b10 I
b10 N
b10000000 6
b10000000 L
b10000000 R
b10 4
b10 B
b10 H
b1 7
b1 C
b1 O
b1 Q
b0 2
0*
1+
1$
#930000
0$
#935000
b100 1
b11 8
b11 I
b11 N
b100 ,
b100 0
b100 =
b0 G
0'
0+
b1 2
b10100000 6
b10100000 L
b10100000 R
b11 4
b11 B
b11 H
b10 7
b10 C
b10 O
b10 Q
b10000000 9
b10000000 M
1$
#940000
0$
#945000
b0 1
b111000 !
b111000 (
b111000 <
b111000 >
b100 2
1)
1$
#950000
0$
#955000
bz !
bz (
bz <
bz >
b1 1
0)
1'
1+
b0 2
1$
#960000
0$
#965000
b101 ,
b101 0
b101 =
b100 8
b100 I
b100 N
b101 1
b10100000 9
b10100000 M
b11000001 6
b11000001 L
b11000001 R
b100 4
b100 B
b100 H
b11 7
b11 C
b11 O
b11 Q
b1 2
0'
0+
1$
#970000
0$
#975000
b0 1
1/
b101 2
1$
#980000
0$
#985000
b110110 :
b110110 F
b110110 J
b1 1
b110110 5
b110110 @
b110110 E
b110111 ;
b110111 ?
b110111 A
b110111 K
b0 2
0/
1'
1+
1$
#990000
0$
#995000
b110 1
b101 8
b101 I
b101 N
b110 ,
b110 0
b110 =
b1 G
0'
0+
b1 2
b11111111 6
b11111111 L
b11111111 R
b101 4
b101 B
b101 H
b100 7
b100 C
b100 O
b100 Q
b11000001 9
b11000001 M
1$
#1000000
0$
#1005000
b0 1
b1 8
b1 I
b1 N
b110 2
1*
1'
1$
#1010000
0$
#1015000
b10 8
b10 I
b10 N
b1 1
0*
1+
b0 2
b10000000 6
b10000000 L
b10000000 R
b10 4
b10 B
b10 H
b1 7
b1 C
b1 O
b1 Q
1$
#1020000
0$
#1025000
b100 ,
b100 0
b100 =
b0 G
b11 8
b11 I
b11 N
b100 1
b10000000 9
b10000000 M
b10100000 6
b10100000 L
b10100000 R
b11 4
b11 B
b11 H
b10 7
b10 C
b10 O
b10 Q
b1 2
0'
0+
1$
#1030000
0$
#1035000
b110111 !
b110111 (
b110111 <
b110111 >
b0 1
1)
b100 2
1$
#1040000
0$
#1045000
b1 1
bz !
bz (
bz <
bz >
b0 2
0)
1'
1+
1$
#1050000
0$
#1055000
b101 1
b100 8
b100 I
b100 N
b101 ,
b101 0
b101 =
0'
0+
b1 2
b11000001 6
b11000001 L
b11000001 R
b100 4
b100 B
b100 H
b11 7
b11 C
b11 O
b11 Q
b10100000 9
b10100000 M
1$
#1060000
0$
#1065000
b0 1
b101 2
1/
1$
#1070000
0$
