数字系统/VS_verilog_源代码文件/verilog/decoder/decoder.v
module decoder (
    input E,
    input [2:0]A,
    output reg [7:0] F

);
    always @(E or A) begin
        if(E) begin
            case (A)
                3'b000: F = 8'b00000001;
                3'b001: F = 8'b00000010;
                3'b010: F = 8'b00000100;
                3'b011: F = 8'b00001000;
                3'b100: F = 8'b00010000;
                3'b101: F = 8'b00100000;
                3'b110: F = 8'b01000000;
                3'b111: F = 8'b10000000;
                
            endcase
        end else begin
            F = 8'b00000000;
        end
    end
endmodule

数字系统/VS_verilog_源代码文件/verilog/decoder/tb.v
//~ `New testbench
`timescale  1ns / 1ps
`include "decoder.v"

module tb_decoder;

// decoder Parameters
parameter PERIOD  = 10;


// decoder Inputs
reg   E                                    = 0 ;
reg   [2:0]  A                             = 0 ;

// decoder Outputs
wire  [7:0]  F                             ;




decoder  u_decoder (
    .E                       ( E        ),
    .A                       ( A  [2:0] ),

    .F                       ( F  [7:0] )
);

initial
begin
$dumpfile("decoder.vcd");
$dumpvars;
E=1;
A=3'b000;
#20;
E=1;
A=3'b001;
#20;
A=3'b010;
#20;
A=3'b011;
#20;
A=3'b100;
#20;
A=3'b101;
#20;
A=3'b110;
#20;
A=3'b111;
#20;
E=0;
A=3'b010;
#20;

    $finish;
end

endmodule

数字系统/VS_verilog_源代码文件/verilog/decoder/decoder.vcd
$date
	Thu Apr 27 23:35:35 2023
$end
$version
	Icarus Verilog
$end
$timescale
	1ps
$end
$scope module tb_decoder $end
$var wire 8 ! F [7:0] $end
$var reg 3 " A [2:0] $end
$var reg 1 # E $end
$scope module u_decoder $end
$var wire 3 $ A [2:0] $end
$var wire 1 # E $end
$var reg 8 % F [7:0] $end
$upscope $end
$upscope $end
$enddefinitions $end
#0
$dumpvars
b1 %
b0 $
1#
b0 "
b1 !
$end
#20000
b10 !
b10 %
b1 "
b1 $
#40000
b100 !
b100 %
b10 "
b10 $
#60000
b1000 !
b1000 %
b11 "
b11 $
#80000
b10000 !
b10000 %
b100 "
b100 $
#100000
b100000 !
b100000 %
b101 "
b101 $
#120000
b1000000 !
b1000000 %
b110 "
b110 $
#140000
b10000000 !
b10000000 %
b111 "
b111 $
#160000
b0 !
b0 %
b10 "
b10 $
0#
