数字系统/VS_verilog_源代码文件/verilog/shiftreg/shiftreg.v
module shiftreg 
#(parameter n = 8)
(
    input clk,
    input shift,
    input serial_in,
    output reg [n-1:0] Q=0
);
  always @(posedge clk ) begin
     if (shift) begin
      Q<={serial_in,Q[n-1:1]};
     end
  end  
endmodule

数字系统/VS_verilog_源代码文件/verilog/shiftreg/tb.v
//~ `New testbench
`include "shiftreg.v"
`timescale  1ns / 1ps

module tb_shiftreg;

// shiftreg Parameters
parameter PERIOD  = 10;
parameter n = 8;


// shiftreg Inputs
reg   clk                                  = 0 ;
reg   shift                                = 0 ;
reg   serial_in                            = 0 ;

// shiftreg Outputs
wire  reg[n-1:0] Q                         ;



initial
begin
    forever #(PERIOD/2)  clk=~clk;
end



shiftreg  u_shiftreg (
    .clk                     ( clk            ),
    .shift                   ( shift          ),
    .serial_in               ( serial_in      ),

    .Q            ( Q  [n-1:0]    )
);

initial
begin
    $dumpfile("tb_shiftreg.vcd");
    $dumpvars(0, tb_shiftreg);
    shift=0;
    #10
    shift=1;
    serial_in=1;
    #10
    serial_in=0;
    #10
    serial_in=1;
    #10
    serial_in=1;
    #5
    shift=0;
    #10
    serial_in=0;
    #10
    serial_in=0;
    #10
    $finish;
end

endmodule

数字系统/VS_verilog_源代码文件/verilog/shiftreg/tb_shiftreg.vcd
$date
	Wed May 03 14:38:24 2023
$end
$version
	Icarus Verilog
$end
$timescale
	1ps
$end
$scope module tb_shiftreg $end
$var wire 8 ! Q [7:0] $end
$var reg 1 " clk $end
$var reg 1 # serial_in $end
$var reg 1 $ shift $end
$scope module u_shiftreg $end
$var wire 1 " clk $end
$var wire 1 # serial_in $end
$var wire 1 $ shift $end
$var reg 8 % Q [7:0] $end
$upscope $end
$upscope $end
$enddefinitions $end
#0
$dumpvars
b0 %
0$
0#
0"
b0 !
$end
#5000
1"
#10000
0"
1#
1$
#15000
b10000000 !
b10000000 %
1"
#20000
0"
0#
#25000
b1000000 !
b1000000 %
1"
#30000
0"
1#
#35000
b10100000 !
b10100000 %
1"
#40000
0"
#45000
1"
0$
#50000
0"
#55000
1"
0#
